{
    "Dr. Bloodmoney": [
        {
            "url": "?tekst=3604",
            "title": "E cobane moj",
            "lyrics": "[<div id=\"content-right\">\n<div id=\"content-padding\">\n<b><a href=\"?izvodjac=247\">Dr. Bloodmoney</a> - E cobane moj</b><br/>\n<br/>A sada sada, za kuma kuma, <br/>I mladu mladu jedna <br/>Slavljenicka cka <br/>Za raspolo\u017eenje \u2013 \u017eenje <br/>Mlado \u017eenje \u017eenje <br/>Idemo idemo : <br/>Skupilo se selo , podigla pra\u0161ina <br/>Zapevala sedla sex ma\u0161ina <br/>Seda udarila gadno \u017eivotom na raju <br/>Nova nada estrade to nastupa u kraju <br/>Navuko narod svoje najbolje odelo <br/>Da pozdravi pevaljke to umetnicko delo <br/>Silna se tu braca okupila da cuju <br/>Kako zvuci dojka kad se ukljuci u struju <br/>Sija \u017eica seva atmosfera vruca <br/>Prsle snajki cvejki preko pluca <br/>Bokal prlja al armonika pegla <br/>Slava udarila sisu pa mikrofon stegla <br/>Upalila mala raj besan dikt <br/>Toliko besan da sve smrdi na \u0161tiht <br/>Snimila gazdu pa za uvcem mu di\u0161e <br/>E cobane moj pa \u0161ta ce ti vi\u0161e <br/>Refren <br/>Sve od istog roja ko od istog tate <br/>U prvi red sele sve videne kravate <br/>Digle im se kite iznad proseka pa \u017eive <br/>Sve kurate face mercedesi i njive <br/>Raduje se mala dok joj pare sise pune <br/>Misli sve dok je ovaca bice i vune <br/>Pa kada prigusti sve rutina je sine <br/>Ako glas nece idu noge u visine <br/>Mlad je bostan rano poceo da vene <br/>Trese refren tresu sise njene <br/>Prosipa se meso sliva rakija po \u0161anku <br/>Udri snajka : daj odradi koju banku <br/>Lete pare leti i mentor kafane <br/>Skocio istog na noge lagane <br/>U\u017eiva raja u estradnoj sisi <br/>E cobane moj , za bolje i nisi <br/>Refren <br/>Debela se po tezgi prosula kinta <br/>Na redu je dojke , ti si poslednja finta <br/>Navuko se narod na merak pa placa, <br/>Ostade im samo \u017euto od gaca <br/>E moj gazda ko je sada radodajka, <br/>Svisnula ti kasa puko si ... <br/>E moj gazda ko je sada radodajka <br/>Svisnula ti kasa puko si ko snajka <br/>Stade muzika , stade ljuti boj <br/>Prso si ko zvecka , e cobane moj <br/>Refren <br/>E cobane moj !<br/><br/><font color=\"green\"><i>- hvala Kastra\u0161</i></font><br/><br/><div style=\"float: none; display: inline-block;\">\n<div style=\"display: inline-block; width: 468px; float: left; margin: 5px 5px 0px 0px; padding: 5px;\">\n<script async=\"\" src=\"//pagead2.googlesyndication.com/pagead/js/adsbygoogle.js\"></script>\n<!-- sv-muz-tekst-468x60 -->\n<ins class=\"adsbygoogle\" data-ad-client=\"ca-pub-7280186603976417\" data-ad-slot=\"4469454054\" style=\"display:inline-block;width:468px;height:60px\"></ins>\n<script>\n\t\t\t\t(adsbygoogle = window.adsbygoogle || []).push({});\n\t\t\t\t</script>\n</div>\n<div id=\"extra\">\n<div style=\"float: none; display: inline-block;\">\n\t\t\t\tPodelite:<br/><a href=\"http://www.facebook.com/sharer.php?u=http%3A%2F%2Fwww.svastara.com%2Fmuzika%2F%3Ftekst%3D3604\"><img alt=\"Share on Facebook\" border=\"0\" src=\"/style/2015/share_facebook.gif\" title=\"Share on Facebook\"/></a>\u00a0\u00a0<a href=\"http://twitter.com/intent/tweet?url=http%3A%2F%2Fwww.svastara.com%2Fmuzika%2F%3Ftekst%3D3604\"><img alt=\"Share on Twitter\" border=\"0\" src=\"/style/2015/share_twitter.gif\" title=\"Share on Twitter\"/></a>\u00a0\u00a0<a href=\"mailto:?subject=Dr. Bloodmoney - E cobane moj tekst&amp;body=http%3A%2F%2Fwww.svastara.com%2Fmuzika%2F%3Ftekst%3D3604\"><img alt=\"Share by e-mail\" border=\"0\" src=\"/style/2015/share_email.gif\" title=\"Share by e-mail\"/></a>\n</div>\n<br/><img src=\"/style/2015/line_green.png\"/>\n<br/>\n<br/><div class=\"sidelist_header\">Popularni tekstovi</div><a href=\"?tekst=12881\" id=\"sidelist\">Pejzazi u magli</a><a href=\"?tekst=3604\" id=\"sidelist\">E cobane moj</a><a href=\"?tekst=5077\" id=\"sidelist\">Milion godina za ljude</a></div></div>\n</div>\n</div>]"
        },
        {
            "url": "?tekst=5077",
            "title": "Milion godina za ljude",
            "lyrics": "[<div id=\"content-right\">\n<div id=\"content-padding\">\n<b><a href=\"?izvodjac=247\">Dr. Bloodmoney</a> - Milion godina za ljude</b><br/>\n<br/>Koliko puta si rekao ma cemu sve ovo<br/>koliko puta pozeleo novo<br/>mislio da si uvek u pravu<br/>da nisi k'o i drugi jer imas pametnu glavu<br/>u cemu je smisao zbog kog bi disao<br/>koliko puta si to sebi opisao<br/>da igra je ovo za vasceli svet<br/>okreni stranu novu, zavrti rulet<br/>pa sta bude na tebi je sve<br/>milio puta si to pozeleo zar ne<br/>odlutao nekud kuda noge te nose<br/>novi list okrenuo sa pravca skrenuo<br/>jer dosadno je biti istog kalupa gena<br/>dosadno je biti masa zavedena<br/>zar se ne pitas nekad kolika je cena<br/>milion godina za ljude<br/><br/>milion godina, milion godina za ljude<br/>milion godina, milion godina za ljude<br/>milion godina, milion godina za ljude<br/>milion godina za sve one sto su bili da ih nikada i ne bude<br/><br/>sto ne bi bio onaj koji karte deli<br/>zrno u vatri sto izgoreti ne zeli<br/>a sto ne bi, zar da budes samo muk<br/>sto ne bi bio kao iz pepela zvuk<br/>a ti ne mrdas, ne dises, stojis prijatelju<br/>a treba uzeti sve<br/>imas zivot na dlanu a slep si i ne vidis<br/>a samo treba reci ne<br/>a sto ne bi ???? ceka i drema<br/>a prijatelju nebo miljenika nema<br/>biti peseban jedan korak je do lud<br/>ova zemlja nije holivud<br/>da ne tren bude neko samo kamo te srece<br/>zivota se ljudi nikad nauciti nece<br/>a vremena jos ima pa neka bude<br/>idu novih milion godina za ljude<br/><br/>milion godina, milion godina za ljude<br/>milion godina, milion godina za ljude<br/>milion godina, milion godina za ljude<br/>milion godina za sve one sto su bili da ih nikada i ne bude<br/><br/>koliko budala toliko i hvala<br/>e moj druze ima ih vala<br/>uvek gladne oci uvek ostri zubi<br/>i sliku svoju kao ikonu ljubi<br/>mozak od gume razumeti ne ume<br/>sta je ne razumes e moj kume<br/>svi imaju svoj lutrije broj<br/>svi zele biti neko gospodine moj<br/>a znas li koliko na svetu takvih ima<br/>biti prvi medju jednakima<br/>milion je malih napoleona<br/>od kad je veka od kad je iskona<br/>izaberi samo um otvori<br/>zar ne osecas da fitilj gori<br/>pa neka sto biti ne moze nek bude<br/>idu novih milion godina za ljude<br/><br/>milion godina, milion godina za ljude<br/>milion godina, milion godina za ljude<br/>milion godina, milion godina za ljude<br/>milion godina za sve one sto su bili da ih nikada i ne bude<br/><br/><font color=\"green\"><i>- hvala Denis BP</i></font><br/><br/><div style=\"float: none; display: inline-block;\">\n<div style=\"display: inline-block; width: 468px; float: left; margin: 5px 5px 0px 0px; padding: 5px;\">\n<script async=\"\" src=\"//pagead2.googlesyndication.com/pagead/js/adsbygoogle.js\"></script>\n<!-- sv-muz-tekst-468x60 -->\n<ins class=\"adsbygoogle\" data-ad-client=\"ca-pub-7280186603976417\" data-ad-slot=\"4469454054\" style=\"display:inline-block;width:468px;height:60px\"></ins>\n<script>\n\t\t\t\t(adsbygoogle = window.adsbygoogle || []).push({});\n\t\t\t\t</script>\n</div>\n<div id=\"extra\">\n<div style=\"float: none; display: inline-block;\">\n\t\t\t\tPodelite:<br/><a href=\"http://www.facebook.com/sharer.php?u=http%3A%2F%2Fwww.svastara.com%2Fmuzika%2F%3Ftekst%3D5077\"><img alt=\"Share on Facebook\" border=\"0\" src=\"/style/2015/share_facebook.gif\" title=\"Share on Facebook\"/></a>\u00a0\u00a0<a href=\"http://twitter.com/intent/tweet?url=http%3A%2F%2Fwww.svastara.com%2Fmuzika%2F%3Ftekst%3D5077\"><img alt=\"Share on Twitter\" border=\"0\" src=\"/style/2015/share_twitter.gif\" title=\"Share on Twitter\"/></a>\u00a0\u00a0<a href=\"mailto:?subject=Dr. Bloodmoney - Milion godina za ljude tekst&amp;body=http%3A%2F%2Fwww.svastara.com%2Fmuzika%2F%3Ftekst%3D5077\"><img alt=\"Share by e-mail\" border=\"0\" src=\"/style/2015/share_email.gif\" title=\"Share by e-mail\"/></a>\n</div>\n<br/><img src=\"/style/2015/line_green.png\"/>\n<br/>\n<br/><div class=\"sidelist_header\">Popularni tekstovi</div><a href=\"?tekst=12881\" id=\"sidelist\">Pejzazi u magli</a><a href=\"?tekst=3604\" id=\"sidelist\">E cobane moj</a><a href=\"?tekst=5077\" id=\"sidelist\">Milion godina za ljude</a></div></div>\n</div>\n</div>]"
        },
        {
            "url": "?tekst=12881",
            "title": "Pejzazi u magli",
            "lyrics": "[<div id=\"content-right\">\n<div id=\"content-padding\">\n<b><a href=\"?izvodjac=247\">Dr. Bloodmoney</a> - Pejzazi u magli</b><br/>\n<br/>Kada ugledam svet shto ga nose rechi tvoje,<br/>i sve one stvari samo tebi shto postoje,<br/>tako razbacane svuda,trag svega shto si bila,<br/>bez reda i smisla,tvoju gomilu debila,<br/>sve one shto ti nude uvek rado igru novu<br/>shto prijatelji tvoji rado kazu da se zovu<br/>shto svaki tvoj pad sebi beleze ko uspon,<br/>i svaki tvoj porok, kao skor,<br/>zar ne vidish to zivota nije boja prava,<br/>to na vrhu igle samo sam djavo spava,<br/>ne budi ga, pusti ga, zaboravi,<br/>al rechi uzalud su,ti vraga nosish u glavi<br/>reci kako je tamo kada sve stane<br/>reci kako je tamo sa druge strane,<br/>reci mi kad zakorachish preko,<br/>dal je lepo biti neko jedan um daleko,<br/>reci mi kad zakorachish preko,<br/>dal je lepo biti neko jedan um daleko,<br/>reci mi dal je lepo biti neko jedan um daleko<br/>reci mi kad zakorachish preko,<br/>dal je lepo biti neko jedan um daleko,<br/>reci mi dal je lepo biti neko jedan um daleko<br/>Mislish pobeci shto dalje kuda pogled samo ide,<br/>ali ochi milosti nemaju,kad ih zatvorish sve vide,<br/>zelish biti neko drugi bolje vrati se sebi<br/>i u gomili si sama nema nikog u tebi,<br/>reci kakav je osecaj izgubiti sve,<br/>i kada proshlost je sva ono par minuta pre,<br/>kada predjesh crtu iza ogledala<br/>u zemlji za Alise, gde milion je budala,<br/>kada odesh _______ sebi da pronadjesh stazu<br/>neku svoju,samo svoju,nad ambisa oazu,<br/>hajde reci kako je ziveti u lazi,<br/>reci koje su boje svi u magli pejzazi<br/>i da li tamo bar postojish sa druge strane,<br/>kako izgleda tamo kada sve stane,<br/>hajde reci dal je lepo biti neko jedan um daleko,<br/>reci mi kad zakorachish preko,<br/>dal je lepo biti neko jedan um daleko,<br/>reci mi dal je lepo biti neko jedan um daleko<br/>reci mi kad zakorachish preko,<br/>dal je lepo biti neko jedan um daleko,<br/>reci mi dal je lepo biti neko jedan um daleko.<br/>Znam da zivota tvog je moto:sam do poslednjeg daha<br/>znam koliko je visoka i tvoja kula od praha,<br/>znam i gde si kada zelish sebi svet neki bolji,<br/>znam i mesto gde je uvek i sve po tvojoj volji,<br/>ali zivot nije zivot kad u njemu sve je lako,<br/>redak je to sluchaj stvari retko idu tako,<br/>nema sporednog puta,nema nazad sve to znam,<br/>znaj, nebo je nad glavom neshto donosi ga grad<br/>svud je beo trag<br/>ispred tebe je zar ne, <br/>shta ce biti na njemu sad na tebi je sve,<br/>al ti to ne vidish znam jedan um tamo preko,<br/>sve shto zelish a to je suvishe daleko,<br/>Pejzazi u magli,a to je suvishe daleko<br/>Pejzazi u magli,a to je suvishe daleko<br/>Pejzazi u magli,a to je suvishe daleko,<br/>a to je suvishe daleko<br/>reci mi kad zakorachish preko,<br/>dal je lepo biti neko jedan um daleko,<br/>reci mi dal je lepo biti neko jedan um daleko<br/>reci mi kad zakorachish preko,<br/>dal je lepo biti neko jedan um daleko,<br/>reci mi dal je lepo biti neko jedan um daleko<br/>jedan um daleko<br/>jedan um daleko<br/>jedan um daleko<br/>jedan um daleko<br/>jedan um daleko<br/><br/>,,Ja mislim da je tekst ovakav, valjda''<br/>-Dinde-<br/><br/><div style=\"float: none; display: inline-block;\">\n<div style=\"display: inline-block; width: 468px; float: left; margin: 5px 5px 0px 0px; padding: 5px;\">\n<script async=\"\" src=\"//pagead2.googlesyndication.com/pagead/js/adsbygoogle.js\"></script>\n<!-- sv-muz-tekst-468x60 -->\n<ins class=\"adsbygoogle\" data-ad-client=\"ca-pub-7280186603976417\" data-ad-slot=\"4469454054\" style=\"display:inline-block;width:468px;height:60px\"></ins>\n<script>\n\t\t\t\t(adsbygoogle = window.adsbygoogle || []).push({});\n\t\t\t\t</script>\n</div>\n<div id=\"extra\">\n<div style=\"float: none; display: inline-block;\">\n\t\t\t\tPodelite:<br/><a href=\"http://www.facebook.com/sharer.php?u=http%3A%2F%2Fwww.svastara.com%2Fmuzika%2F%3Ftekst%3D12881\"><img alt=\"Share on Facebook\" border=\"0\" src=\"/style/2015/share_facebook.gif\" title=\"Share on Facebook\"/></a>\u00a0\u00a0<a href=\"http://twitter.com/intent/tweet?url=http%3A%2F%2Fwww.svastara.com%2Fmuzika%2F%3Ftekst%3D12881\"><img alt=\"Share on Twitter\" border=\"0\" src=\"/style/2015/share_twitter.gif\" title=\"Share on Twitter\"/></a>\u00a0\u00a0<a href=\"mailto:?subject=Dr. Bloodmoney - Pejzazi u magli tekst&amp;body=http%3A%2F%2Fwww.svastara.com%2Fmuzika%2F%3Ftekst%3D12881\"><img alt=\"Share by e-mail\" border=\"0\" src=\"/style/2015/share_email.gif\" title=\"Share by e-mail\"/></a>\n</div>\n<br/><img src=\"/style/2015/line_green.png\"/>\n<br/>\n<br/><div class=\"sidelist_header\">Popularni tekstovi</div><a href=\"?tekst=12881\" id=\"sidelist\">Pejzazi u magli</a><a href=\"?tekst=3604\" id=\"sidelist\">E cobane moj</a><a href=\"?tekst=5077\" id=\"sidelist\">Milion godina za ljude</a></div></div>\n</div>\n</div>]"
        }
    ]
}