{
    "Flare": [
        {
            "url": "?tekst=6207",
            "title": "\u010cekanje",
            "lyrics": "[<div id=\"content-right\">\n<div id=\"content-padding\">\n<b><a href=\"?izvodjac=455\">Flare</a> - \u010cekanje</b><br/>\n<br/>Vidim te,u \u010dudnom obliku vizije<br/>tvoj dah zamagljuje mi prozore<br/>Gledam te, smi\u0161lja\u0161 nove prepreke<br/>u gradu Sunca tebi hladno je...<br/><br/>Nasmije\u0161i se<br/>ovdje nikog nema ko te poznaje<br/>a zrak kao da miri\u0161e <br/>na jabuke<br/><br/>Daleko<br/>dovoljno daleko da nam rije\u010di ni\u0161ta<br/>ne zna\u010de<br/>slu\u0161a\u010du sa susjedne stolice<br/><br/>Opusti se<br/>ne daj da te misli odvode<br/>tek si stigla a vi\u0161e ti se i ne ostaje<br/><br/>Sunce<br/>\u017eutom boji ulice<br/>Prolazi\u0161<br/>sive su ti haljine<br/>Crveno<br/>miri\u0161e nam predve\u010de<br/>Odlazi\u0161<br/>nervira te \u010dekanje<br/><br/>\u010cekanje<br/>sve \u0161to radi\u0161 to je \u010dekanje<br/>Tek si stigla a vi\u0161e ti se i ne ostaje<br/>Sunce<br/>\u017eutom boji ulice<br/>Prolazi\u0161<br/>sive su ti haljine<br/>Crveno<br/>miri\u0161e nam predve\u010de<br/>Odlazi\u0161<br/>nervira te \u010dekanje<br/>\u010cekanje...<br/><br/><font color=\"green\"><i>- hvala Ivona</i></font><br/><br/><div style=\"float: none; display: inline-block;\">\n<div style=\"display: inline-block; width: 468px; float: left; margin: 5px 5px 0px 0px; padding: 5px;\">\n<script async=\"\" src=\"//pagead2.googlesyndication.com/pagead/js/adsbygoogle.js\"></script>\n<!-- sv-muz-tekst-468x60 -->\n<ins class=\"adsbygoogle\" data-ad-client=\"ca-pub-7280186603976417\" data-ad-slot=\"4469454054\" style=\"display:inline-block;width:468px;height:60px\"></ins>\n<script>\n\t\t\t\t(adsbygoogle = window.adsbygoogle || []).push({});\n\t\t\t\t</script>\n</div>\n<div id=\"extra\">\n<div style=\"float: none; display: inline-block;\">\n\t\t\t\tPodelite:<br/><a href=\"http://www.facebook.com/sharer.php?u=http%3A%2F%2Fwww.svastara.com%2Fmuzika%2F%3Ftekst%3D6207\"><img alt=\"Share on Facebook\" border=\"0\" src=\"/style/2015/share_facebook.gif\" title=\"Share on Facebook\"/></a>\u00a0\u00a0<a href=\"http://twitter.com/intent/tweet?url=http%3A%2F%2Fwww.svastara.com%2Fmuzika%2F%3Ftekst%3D6207\"><img alt=\"Share on Twitter\" border=\"0\" src=\"/style/2015/share_twitter.gif\" title=\"Share on Twitter\"/></a>\u00a0\u00a0<a href=\"mailto:?subject=Flare - \u010cekanje tekst&amp;body=http%3A%2F%2Fwww.svastara.com%2Fmuzika%2F%3Ftekst%3D6207\"><img alt=\"Share by e-mail\" border=\"0\" src=\"/style/2015/share_email.gif\" title=\"Share by e-mail\"/></a>\n</div>\n<br/><img src=\"/style/2015/line_green.png\"/>\n<br/>\n<br/><div class=\"sidelist_header\">Popularni tekstovi</div><a href=\"?tekst=6201\" id=\"sidelist\">Srebrni</a><a href=\"?tekst=10667\" id=\"sidelist\">Zaista</a><a href=\"?tekst=6206\" id=\"sidelist\">Dimom u o\u010di</a><a href=\"?tekst=9673\" id=\"sidelist\">Poslednja zelja</a><a href=\"?tekst=6205\" id=\"sidelist\">More</a><a href=\"?tekst=6204\" id=\"sidelist\">Nova doza</a><a href=\"?tekst=6203\" id=\"sidelist\">Ostajem jaka</a></div></div>\n</div>\n</div>]"
        },
        {
            "url": "?tekst=6206",
            "title": "Dimom u o\u010di",
            "lyrics": "[<div id=\"content-right\">\n<div id=\"content-padding\">\n<b><a href=\"?izvodjac=455\">Flare</a> - Dimom u o\u010di</b><br/>\n<br/>Predamnom ne mora\u0161 kle\u010dati<br/>te\u0161ke rije\u010di govoriti<br/>\u0160to je bilo zaboravi<br/>to su okovi pro\u0161losti<br/><br/>Dugo nismo se vidjeli<br/>a lagati te ne mogu<br/>U mome filmu davno si<br/>izgubio ulogu<br/><br/>Sad opet do\u0161ao si <br/>paliti u meni<br/>neobuzdane po\u017eare<br/><br/>Pred jutro mi ponudi<br/>divlje cvije\u0107e sa livade<br/>koje \u0107e osvije\u017eiti <br/>nas oboje<br/><br/>Sad opet do\u0161ao si <br/>paliti u meni<br/>neobuzdane po\u017eare<br/><br/>Zato ne gledaj me<br/>tu\u017enim o\u010dima<br/>sada kad saznaje\u0161<br/>da je sve zabluda<br/>zabluda...<br/><br/>Samo dimom u o\u010di<br/>tvoje postupke ja vra\u0107am ti<br/>sada zaboravi<br/>\u0161to si samnom htio posti\u0107i<br/>samo dimom u o\u010di...<br/><br/><font color=\"green\"><i>- hvala Ivona</i></font><br/><br/><br/><div style=\"float: none; display: inline-block;\">\n<div id=\"extra\">\n<div style=\"float: none; display: inline-block;\">\n\t\t\t\tPodelite:<br/><a href=\"http://www.facebook.com/sharer.php?u=http%3A%2F%2Fwww.svastara.com%2Fmuzika%2F%3Ftekst%3D6206\"><img alt=\"Share on Facebook\" border=\"0\" src=\"/style/2015/share_facebook.gif\" title=\"Share on Facebook\"/></a>\u00a0\u00a0<a href=\"http://twitter.com/intent/tweet?url=http%3A%2F%2Fwww.svastara.com%2Fmuzika%2F%3Ftekst%3D6206\"><img alt=\"Share on Twitter\" border=\"0\" src=\"/style/2015/share_twitter.gif\" title=\"Share on Twitter\"/></a>\u00a0\u00a0<a href=\"mailto:?subject=Flare - Dimom u o\u010di tekst&amp;body=http%3A%2F%2Fwww.svastara.com%2Fmuzika%2F%3Ftekst%3D6206\"><img alt=\"Share by e-mail\" border=\"0\" src=\"/style/2015/share_email.gif\" title=\"Share by e-mail\"/></a>\n</div>\n<br/><img src=\"/style/2015/line_green.png\"/>\n<br/>\n<br/><div class=\"sidelist_header\">Popularni tekstovi</div><a href=\"?tekst=6201\" id=\"sidelist\">Srebrni</a><a href=\"?tekst=10667\" id=\"sidelist\">Zaista</a><a href=\"?tekst=6206\" id=\"sidelist\">Dimom u o\u010di</a><a href=\"?tekst=9673\" id=\"sidelist\">Poslednja zelja</a><a href=\"?tekst=6205\" id=\"sidelist\">More</a><a href=\"?tekst=6204\" id=\"sidelist\">Nova doza</a><a href=\"?tekst=6203\" id=\"sidelist\">Ostajem jaka</a></div>\n<div id=\"extra\">\n<script async=\"\" src=\"//pagead2.googlesyndication.com/pagead/js/adsbygoogle.js\"></script>\n<!-- sv-muz-tekst-300x250 -->\n<ins class=\"adsbygoogle\" data-ad-client=\"ca-pub-7280186603976417\" data-ad-slot=\"4744088596\" style=\"display:inline-block;width:300px;height:250px\"></ins>\n<script>\n\t\t\t\t(adsbygoogle = window.adsbygoogle || []).push({});\n\t\t\t\t</script>\n</div></div>\n</div>\n</div>]"
        },
        {
            "url": "?tekst=6205",
            "title": "More",
            "lyrics": "[<div id=\"content-right\">\n<div id=\"content-padding\">\n<b><a href=\"?izvodjac=455\">Flare</a> - More</b><br/>\n<br/>Potra\u017ei me<br/>zna\u0161 da sam negdje blizu, zna\u0161 da uvijek sam blizu<br/>Prona\u0111i me<br/>u svakome svome danu, ja u svakom tvome danu bi\u0107u<br/>Zaklopi o\u010di<br/>i otvori u\u0161i i slu\u0161aj me, osjeti da gledam te i<br/>Priznajem<br/>ve\u0107 dugo \u010dekam te...<br/><br/>O more je mra\u010dno, valovi ne daju spas<br/>kroz maglu te vidim, reci sa \u010duje\u0161 moj glas<br/>Ja bi\u0107u tvoj otok, bi\u0107u tvoj posljednji spas<br/>Za tebe ja \u010duvam svoj posljednji dah<br/><br/>\u010cini se<br/>ko da se nikada prije nismo sreli, ne\u0107emo se sresti <br/>mo\u017eda...kasno je, kasno je<br/>Ti tra\u017ei me<br/>na jednom od tvojih puteva bi\u0107u, jedna od stanica tvojih<br/>Ja sam<br/>zaustavi se, prepoznaj me<br/>upoznaj me, upoznaj me...<br/><br/>O more je mra\u010dno, valovi ne daju spas<br/>kroz maglu te vidim, reci sa \u010duje\u0161 moj glas<br/>Ja bi\u0107u tvoj otok, bi\u0107u tvoj posljednji spas<br/>Za tebe ja \u010duvam svoj posljednji dah<br/><br/><font color=\"green\"><i>- hvala Ivona</i></font><br/><br/><br/><div style=\"float: none; display: inline-block;\">\n<div id=\"extra\">\n<div style=\"float: none; display: inline-block;\">\n\t\t\t\tPodelite:<br/><a href=\"http://www.facebook.com/sharer.php?u=http%3A%2F%2Fwww.svastara.com%2Fmuzika%2F%3Ftekst%3D6205\"><img alt=\"Share on Facebook\" border=\"0\" src=\"/style/2015/share_facebook.gif\" title=\"Share on Facebook\"/></a>\u00a0\u00a0<a href=\"http://twitter.com/intent/tweet?url=http%3A%2F%2Fwww.svastara.com%2Fmuzika%2F%3Ftekst%3D6205\"><img alt=\"Share on Twitter\" border=\"0\" src=\"/style/2015/share_twitter.gif\" title=\"Share on Twitter\"/></a>\u00a0\u00a0<a href=\"mailto:?subject=Flare - More tekst&amp;body=http%3A%2F%2Fwww.svastara.com%2Fmuzika%2F%3Ftekst%3D6205\"><img alt=\"Share by e-mail\" border=\"0\" src=\"/style/2015/share_email.gif\" title=\"Share by e-mail\"/></a>\n</div>\n<br/><img src=\"/style/2015/line_green.png\"/>\n<br/>\n<br/><div class=\"sidelist_header\">Popularni tekstovi</div><a href=\"?tekst=6201\" id=\"sidelist\">Srebrni</a><a href=\"?tekst=10667\" id=\"sidelist\">Zaista</a><a href=\"?tekst=6206\" id=\"sidelist\">Dimom u o\u010di</a><a href=\"?tekst=9673\" id=\"sidelist\">Poslednja zelja</a><a href=\"?tekst=6205\" id=\"sidelist\">More</a><a href=\"?tekst=6204\" id=\"sidelist\">Nova doza</a><a href=\"?tekst=6203\" id=\"sidelist\">Ostajem jaka</a></div>\n<div id=\"extra\">\n<script async=\"\" src=\"//pagead2.googlesyndication.com/pagead/js/adsbygoogle.js\"></script>\n<!-- sv-muz-tekst-300x250 -->\n<ins class=\"adsbygoogle\" data-ad-client=\"ca-pub-7280186603976417\" data-ad-slot=\"4744088596\" style=\"display:inline-block;width:300px;height:250px\"></ins>\n<script>\n\t\t\t\t(adsbygoogle = window.adsbygoogle || []).push({});\n\t\t\t\t</script>\n</div></div>\n</div>\n</div>]"
        },
        {
            "url": "?tekst=6204",
            "title": "Nova doza",
            "lyrics": "[<div id=\"content-right\">\n<div id=\"content-padding\">\n<b><a href=\"?izvodjac=455\">Flare</a> - Nova doza</b><br/>\n<br/>Svi su po\u010deci  ko i krajevi isti<br/>kada je po\u010delo i gdje treba stati<br/>\u017divim sve br\u017ee, radim tisu\u0107u stvari<br/>Tra\u017eim te svugdje, ne mogu, ne mogu te na\u0107i<br/><br/>Tvoja su jutra i \u010deka\u0161 me u no\u0107i<br/>U za\u010daranom krugu sam<br/>Ne mogu, ne mogu iza\u0107i<br/><br/>Opet biram tvoj broj<br/>Halo \u010duje\u0161 li me, dolazim<br/>Sve \u0161to trebam je nova<br/>doza ljubavi<br/><br/> Svi su po\u010deci  ko i krajevi isti<br/>kada je po\u010delo i gdje treba stati<br/><br/>Opet biram tvoj broj<br/>Halo \u010duje\u0161 li me, dolazim<br/>Sve \u0161to trebam je nova<br/>doza ljubavi<br/><br/><font color=\"green\"><i>- hvala Ivona</i></font><br/><br/><div style=\"float: none; display: inline-block;\">\n<div style=\"display: inline-block; width: 468px; float: left; margin: 5px 5px 0px 0px; padding: 5px;\">\n<script async=\"\" src=\"//pagead2.googlesyndication.com/pagead/js/adsbygoogle.js\"></script>\n<!-- sv-muz-tekst-468x60 -->\n<ins class=\"adsbygoogle\" data-ad-client=\"ca-pub-7280186603976417\" data-ad-slot=\"4469454054\" style=\"display:inline-block;width:468px;height:60px\"></ins>\n<script>\n\t\t\t\t(adsbygoogle = window.adsbygoogle || []).push({});\n\t\t\t\t</script>\n</div>\n<div id=\"extra\">\n<div style=\"float: none; display: inline-block;\">\n\t\t\t\tPodelite:<br/><a href=\"http://www.facebook.com/sharer.php?u=http%3A%2F%2Fwww.svastara.com%2Fmuzika%2F%3Ftekst%3D6204\"><img alt=\"Share on Facebook\" border=\"0\" src=\"/style/2015/share_facebook.gif\" title=\"Share on Facebook\"/></a>\u00a0\u00a0<a href=\"http://twitter.com/intent/tweet?url=http%3A%2F%2Fwww.svastara.com%2Fmuzika%2F%3Ftekst%3D6204\"><img alt=\"Share on Twitter\" border=\"0\" src=\"/style/2015/share_twitter.gif\" title=\"Share on Twitter\"/></a>\u00a0\u00a0<a href=\"mailto:?subject=Flare - Nova doza tekst&amp;body=http%3A%2F%2Fwww.svastara.com%2Fmuzika%2F%3Ftekst%3D6204\"><img alt=\"Share by e-mail\" border=\"0\" src=\"/style/2015/share_email.gif\" title=\"Share by e-mail\"/></a>\n</div>\n<br/><img src=\"/style/2015/line_green.png\"/>\n<br/>\n<br/><div class=\"sidelist_header\">Popularni tekstovi</div><a href=\"?tekst=6201\" id=\"sidelist\">Srebrni</a><a href=\"?tekst=10667\" id=\"sidelist\">Zaista</a><a href=\"?tekst=6206\" id=\"sidelist\">Dimom u o\u010di</a><a href=\"?tekst=9673\" id=\"sidelist\">Poslednja zelja</a><a href=\"?tekst=6205\" id=\"sidelist\">More</a><a href=\"?tekst=6204\" id=\"sidelist\">Nova doza</a><a href=\"?tekst=6203\" id=\"sidelist\">Ostajem jaka</a></div></div>\n</div>\n</div>]"
        },
        {
            "url": "?tekst=6203",
            "title": "Ostajem jaka",
            "lyrics": "[<div id=\"content-right\">\n<div id=\"content-padding\">\n<b><a href=\"?izvodjac=455\">Flare</a> - Ostajem jaka</b><br/>\n<br/>U sobu ulazim, prestajem misliti<br/>znam da tamo iza vrata jo\u0161 uvijek \u010deka\u0161 me ti<br/>\u017eeljela bih vri\u0161tati ali glas i osje\u0107aji svi su nestali<br/><br/>I ne\u0107e me boljeti kada zatvorim o\u010di i <br/>vidim da gleda\u0161 me ti<br/>Tvoju ruku u ruci ja osje\u0107am i<br/>Vi\u0161e nisam sama, od sada vodi\u0161 me ti<br/><br/>Prestajem disati, o\u010di zatvaram<br/>Strahove tjeram od sebe<br/>Ostajem jaka<br/>Prestajem disati, o\u010di zatvaram<br/>Strahove tjeram od sebe<br/><br/>Tvoje ruke vode me kroz snove<br/>daleko od straha<br/>Sada znam da vi\u0161e nikada ne\u0107u,<br/>ne\u0107u biti sama<br/><br/>Prestajem disati, o\u010di zatvaram<br/>Strahove tjeram od sebe<br/>Ostajem jaka<br/><br/><font color=\"green\"><i>- hvala Ivona</i></font><br/><br/><div style=\"float: none; display: inline-block;\">\n<div style=\"display: inline-block; width: 468px; float: left; margin: 5px 5px 0px 0px; padding: 5px;\">\n<script async=\"\" src=\"//pagead2.googlesyndication.com/pagead/js/adsbygoogle.js\"></script>\n<!-- sv-muz-tekst-468x60 -->\n<ins class=\"adsbygoogle\" data-ad-client=\"ca-pub-7280186603976417\" data-ad-slot=\"4469454054\" style=\"display:inline-block;width:468px;height:60px\"></ins>\n<script>\n\t\t\t\t(adsbygoogle = window.adsbygoogle || []).push({});\n\t\t\t\t</script>\n</div>\n<div id=\"extra\">\n<div style=\"float: none; display: inline-block;\">\n\t\t\t\tPodelite:<br/><a href=\"http://www.facebook.com/sharer.php?u=http%3A%2F%2Fwww.svastara.com%2Fmuzika%2F%3Ftekst%3D6203\"><img alt=\"Share on Facebook\" border=\"0\" src=\"/style/2015/share_facebook.gif\" title=\"Share on Facebook\"/></a>\u00a0\u00a0<a href=\"http://twitter.com/intent/tweet?url=http%3A%2F%2Fwww.svastara.com%2Fmuzika%2F%3Ftekst%3D6203\"><img alt=\"Share on Twitter\" border=\"0\" src=\"/style/2015/share_twitter.gif\" title=\"Share on Twitter\"/></a>\u00a0\u00a0<a href=\"mailto:?subject=Flare - Ostajem jaka tekst&amp;body=http%3A%2F%2Fwww.svastara.com%2Fmuzika%2F%3Ftekst%3D6203\"><img alt=\"Share by e-mail\" border=\"0\" src=\"/style/2015/share_email.gif\" title=\"Share by e-mail\"/></a>\n</div>\n<br/><img src=\"/style/2015/line_green.png\"/>\n<br/>\n<br/><div class=\"sidelist_header\">Popularni tekstovi</div><a href=\"?tekst=6201\" id=\"sidelist\">Srebrni</a><a href=\"?tekst=10667\" id=\"sidelist\">Zaista</a><a href=\"?tekst=6206\" id=\"sidelist\">Dimom u o\u010di</a><a href=\"?tekst=9673\" id=\"sidelist\">Poslednja zelja</a><a href=\"?tekst=6205\" id=\"sidelist\">More</a><a href=\"?tekst=6204\" id=\"sidelist\">Nova doza</a><a href=\"?tekst=6203\" id=\"sidelist\">Ostajem jaka</a></div></div>\n</div>\n</div>]"
        },
        {
            "url": "?tekst=9673",
            "title": "Poslednja zelja",
            "lyrics": "[<div id=\"content-right\">\n<div id=\"content-padding\">\n<b><a href=\"?izvodjac=455\">Flare</a> - Poslednja zelja</b><br/>\n<br/>Bilo..,bilo kada mozes doci<br/>i poput morske vode<br/>svoju sjenu mi natoci <br/>na ruke umorne<br/><br/>Straza,straza drzi me u zamku<br/>ne daju mi da te dotaknem<br/>ne daju ti da me odvedes<br/><br/>Budi snazan<br/>Budi hrabar<br/>Budi moj<br/>Zauvijek,zauvijek,zauvijek,zau....<br/><br/>Straza,straza sada mirno spava<br/>serum tece njihovim zilama<br/>vodi ih vilenjak,vodi vilenjak<br/><br/>Kroz hodnik cujem snazne korake<br/>glasno dises,cujem zovem te<br/>jos  samo jedan strazar budan je<br/>svoje strijele salje na mene,<br/>cilja,one prolaze...<br/><br/>Poslednja zelja,poslednja stvar<br/>je da dodirnem jednom ocean<br/>s delfinima  zaplivam<br/>poslednja zelja,poslednja stvar<br/>je da dodirnem tvoje lice<br/>i sa tobom otplivam<br/><br/>Poslednaj zelja,poslednja stvar<br/>je da dodirnem jednom ocean<br/>s delfinima zaplivam<br/>Poslednja zelja,poslednja stvar<br/>je da dodirnem tvoje lice <br/>i sa tobom otplivam<br/><br/>Zauvijek,zauvijek...<br/><br/><font color=\"green\"><i>- hvala Melisa</i></font><br/><br/><div style=\"float: none; display: inline-block;\">\n<div style=\"display: inline-block; width: 468px; float: left; margin: 5px 5px 0px 0px; padding: 5px;\">\n<script async=\"\" src=\"//pagead2.googlesyndication.com/pagead/js/adsbygoogle.js\"></script>\n<!-- sv-muz-tekst-468x60 -->\n<ins class=\"adsbygoogle\" data-ad-client=\"ca-pub-7280186603976417\" data-ad-slot=\"4469454054\" style=\"display:inline-block;width:468px;height:60px\"></ins>\n<script>\n\t\t\t\t(adsbygoogle = window.adsbygoogle || []).push({});\n\t\t\t\t</script>\n</div>\n<div id=\"extra\">\n<div style=\"float: none; display: inline-block;\">\n\t\t\t\tPodelite:<br/><a href=\"http://www.facebook.com/sharer.php?u=http%3A%2F%2Fwww.svastara.com%2Fmuzika%2F%3Ftekst%3D9673\"><img alt=\"Share on Facebook\" border=\"0\" src=\"/style/2015/share_facebook.gif\" title=\"Share on Facebook\"/></a>\u00a0\u00a0<a href=\"http://twitter.com/intent/tweet?url=http%3A%2F%2Fwww.svastara.com%2Fmuzika%2F%3Ftekst%3D9673\"><img alt=\"Share on Twitter\" border=\"0\" src=\"/style/2015/share_twitter.gif\" title=\"Share on Twitter\"/></a>\u00a0\u00a0<a href=\"mailto:?subject=Flare - Poslednja zelja tekst&amp;body=http%3A%2F%2Fwww.svastara.com%2Fmuzika%2F%3Ftekst%3D9673\"><img alt=\"Share by e-mail\" border=\"0\" src=\"/style/2015/share_email.gif\" title=\"Share by e-mail\"/></a>\n</div>\n<br/><img src=\"/style/2015/line_green.png\"/>\n<br/>\n<br/><div class=\"sidelist_header\">Popularni tekstovi</div><a href=\"?tekst=6201\" id=\"sidelist\">Srebrni</a><a href=\"?tekst=10667\" id=\"sidelist\">Zaista</a><a href=\"?tekst=6206\" id=\"sidelist\">Dimom u o\u010di</a><a href=\"?tekst=9673\" id=\"sidelist\">Poslednja zelja</a><a href=\"?tekst=6205\" id=\"sidelist\">More</a><a href=\"?tekst=6204\" id=\"sidelist\">Nova doza</a><a href=\"?tekst=6203\" id=\"sidelist\">Ostajem jaka</a></div></div>\n</div>\n</div>]"
        },
        {
            "url": "?tekst=6202",
            "title": "Pustinje",
            "lyrics": "[<div id=\"content-right\">\n<div id=\"content-padding\">\n<b><a href=\"?izvodjac=455\">Flare</a> - Pustinje</b><br/>\n<br/>Jo\u0161 samo jedan dan nam preostaje<br/>i kako sada dalje<br/>Uvijek isto pitanje<br/>(tako tiho) prisutan pru\u017ea\u0161 mi utjehu<br/>Budi uvijek tu kad oluje nai\u0111u<br/><br/>Tvoje tragove u pijesku vjetar odnosi<br/>ali bilo kuda idem znam da samnom si uvijek ti<br/>tako tiho prisutan pru\u017ea\u0161 mi utjehu<br/>Samo budi uvijek tu kad oluje nai\u0111u<br/><br/>Jo\u0161 samo jedan dan preostaje<br/>s tobom brzo sati prolaze<br/>Zagrli me i ne pu\u0161taj me u pustinje<br/><br/><font color=\"green\"><i>- hvala Ivona</i></font><br/><br/><div style=\"float: none; display: inline-block;\">\n<div style=\"display: inline-block; width: 468px; float: left; margin: 5px 5px 0px 0px; padding: 5px;\">\n<script async=\"\" src=\"//pagead2.googlesyndication.com/pagead/js/adsbygoogle.js\"></script>\n<!-- sv-muz-tekst-468x60 -->\n<ins class=\"adsbygoogle\" data-ad-client=\"ca-pub-7280186603976417\" data-ad-slot=\"4469454054\" style=\"display:inline-block;width:468px;height:60px\"></ins>\n<script>\n\t\t\t\t(adsbygoogle = window.adsbygoogle || []).push({});\n\t\t\t\t</script>\n</div>\n<div id=\"extra\">\n<div style=\"float: none; display: inline-block;\">\n\t\t\t\tPodelite:<br/><a href=\"http://www.facebook.com/sharer.php?u=http%3A%2F%2Fwww.svastara.com%2Fmuzika%2F%3Ftekst%3D6202\"><img alt=\"Share on Facebook\" border=\"0\" src=\"/style/2015/share_facebook.gif\" title=\"Share on Facebook\"/></a>\u00a0\u00a0<a href=\"http://twitter.com/intent/tweet?url=http%3A%2F%2Fwww.svastara.com%2Fmuzika%2F%3Ftekst%3D6202\"><img alt=\"Share on Twitter\" border=\"0\" src=\"/style/2015/share_twitter.gif\" title=\"Share on Twitter\"/></a>\u00a0\u00a0<a href=\"mailto:?subject=Flare - Pustinje tekst&amp;body=http%3A%2F%2Fwww.svastara.com%2Fmuzika%2F%3Ftekst%3D6202\"><img alt=\"Share by e-mail\" border=\"0\" src=\"/style/2015/share_email.gif\" title=\"Share by e-mail\"/></a>\n</div>\n<br/><img src=\"/style/2015/line_green.png\"/>\n<br/>\n<br/><div class=\"sidelist_header\">Popularni tekstovi</div><a href=\"?tekst=6201\" id=\"sidelist\">Srebrni</a><a href=\"?tekst=10667\" id=\"sidelist\">Zaista</a><a href=\"?tekst=6206\" id=\"sidelist\">Dimom u o\u010di</a><a href=\"?tekst=9673\" id=\"sidelist\">Poslednja zelja</a><a href=\"?tekst=6205\" id=\"sidelist\">More</a><a href=\"?tekst=6204\" id=\"sidelist\">Nova doza</a><a href=\"?tekst=6203\" id=\"sidelist\">Ostajem jaka</a></div></div>\n</div>\n</div>]"
        },
        {
            "url": "?tekst=6201",
            "title": "Srebrni",
            "lyrics": "[<div id=\"content-right\">\n<div id=\"content-padding\">\n<b><a href=\"?izvodjac=455\">Flare</a> - Srebrni</b><br/>\n<br/>Srebrni, srebrni snijeg je zasuo ulicu<br/>Tragove, tragove odnose vjetrovi<br/>Zauvijek\u2026<br/><br/>Hladno je, zagrij mi ruke, sakrij me<br/>Da me ne vide<br/>Nedostaje\u0161 mi<br/>Mada te mrzim, voljet htjela bi<br/><br/>Ponekad sanjam da tu si kraj mene<br/>i opet sam sama<br/>Ja ne zaslu\u017eujem strah <br/><br/>Ponekad vidim te yeah<br/>kad zaklopim o\u010di i zamislim te<br/>\u017delim da bje\u017eim<br/>al na tebe podsje\u0107a me<br/><br/>I prvi put kao da zaista znam<br/>da postoji sutra, da postoji dan<br/>kad \u0107e\u0161 do\u0107i i re\u0107i mi<br/><br/>Srebrni, srebrni snijeg je zasuo ulicu<br/>Nedostaje\u0161 mi<br/>Mada te mrzim, voljet htjela bi<br/><br/>Ponekad sanjam da tu si kraj mene<br/>i opet sam sama<br/>Ja ne zaslu\u017eujem strah<br/><br/> Ponekad vidim te yeah<br/>kad zaklopim o\u010di i zamislim te<br/>\u017delim da bje\u017eim<br/>al na tebe podsje\u0107a me<br/><br/>I prvi put kao da zaista znam<br/>da postoji sutra, da postoji dan<br/>kad \u0107e\u0161 do\u0107i i re\u0107i mi<br/>Srebrni\u2026<br/><br/><font color=\"green\"><i>- hvala Ivona</i></font><br/><br/><br/><div style=\"float: none; display: inline-block;\">\n<div id=\"extra\">\n<div style=\"float: none; display: inline-block;\">\n\t\t\t\tPodelite:<br/><a href=\"http://www.facebook.com/sharer.php?u=http%3A%2F%2Fwww.svastara.com%2Fmuzika%2F%3Ftekst%3D6201\"><img alt=\"Share on Facebook\" border=\"0\" src=\"/style/2015/share_facebook.gif\" title=\"Share on Facebook\"/></a>\u00a0\u00a0<a href=\"http://twitter.com/intent/tweet?url=http%3A%2F%2Fwww.svastara.com%2Fmuzika%2F%3Ftekst%3D6201\"><img alt=\"Share on Twitter\" border=\"0\" src=\"/style/2015/share_twitter.gif\" title=\"Share on Twitter\"/></a>\u00a0\u00a0<a href=\"mailto:?subject=Flare - Srebrni tekst&amp;body=http%3A%2F%2Fwww.svastara.com%2Fmuzika%2F%3Ftekst%3D6201\"><img alt=\"Share by e-mail\" border=\"0\" src=\"/style/2015/share_email.gif\" title=\"Share by e-mail\"/></a>\n</div>\n<br/><img src=\"/style/2015/line_green.png\"/>\n<br/>\n<br/><div class=\"sidelist_header\">Popularni tekstovi</div><a href=\"?tekst=6201\" id=\"sidelist\">Srebrni</a><a href=\"?tekst=10667\" id=\"sidelist\">Zaista</a><a href=\"?tekst=6206\" id=\"sidelist\">Dimom u o\u010di</a><a href=\"?tekst=9673\" id=\"sidelist\">Poslednja zelja</a><a href=\"?tekst=6205\" id=\"sidelist\">More</a><a href=\"?tekst=6204\" id=\"sidelist\">Nova doza</a><a href=\"?tekst=6203\" id=\"sidelist\">Ostajem jaka</a></div>\n<div id=\"extra\">\n<script async=\"\" src=\"//pagead2.googlesyndication.com/pagead/js/adsbygoogle.js\"></script>\n<!-- sv-muz-tekst-300x250 -->\n<ins class=\"adsbygoogle\" data-ad-client=\"ca-pub-7280186603976417\" data-ad-slot=\"4744088596\" style=\"display:inline-block;width:300px;height:250px\"></ins>\n<script>\n\t\t\t\t(adsbygoogle = window.adsbygoogle || []).push({});\n\t\t\t\t</script>\n</div></div>\n</div>\n</div>]"
        },
        {
            "url": "?tekst=6200",
            "title": "Waiting",
            "lyrics": "[<div id=\"content-right\">\n<div id=\"content-padding\">\n<b><a href=\"?izvodjac=455\">Flare</a> - Waiting</b><br/>\n<br/>I\u2019m used to feeling alone in a room full of people<br/>And not to have you close<br/>While what everybody talks about is love<br/><br/>And I can\u2019t stand to watch the couple right next to me<br/>I can\u2019t seem to be the person I used to be<br/><br/>Whatever I say, whatever I do, I\u2019ll wait for you<br/>And don\u2019t be afraid, I won\u2019t let it down<br/>I\u2019ll wait for you<br/><br/>No matter what you do, <br/>no matter how long you stay<br/>no matter what they say<br/>I will be waiting<br/><br/><font color=\"green\"><i>- hvala Ivona</i></font><br/><br/><div style=\"float: none; display: inline-block;\">\n<div style=\"display: inline-block; width: 468px; float: left; margin: 5px 5px 0px 0px; padding: 5px;\">\n<script async=\"\" src=\"//pagead2.googlesyndication.com/pagead/js/adsbygoogle.js\"></script>\n<!-- sv-muz-tekst-468x60 -->\n<ins class=\"adsbygoogle\" data-ad-client=\"ca-pub-7280186603976417\" data-ad-slot=\"4469454054\" style=\"display:inline-block;width:468px;height:60px\"></ins>\n<script>\n\t\t\t\t(adsbygoogle = window.adsbygoogle || []).push({});\n\t\t\t\t</script>\n</div>\n<div id=\"extra\">\n<div style=\"float: none; display: inline-block;\">\n\t\t\t\tPodelite:<br/><a href=\"http://www.facebook.com/sharer.php?u=http%3A%2F%2Fwww.svastara.com%2Fmuzika%2F%3Ftekst%3D6200\"><img alt=\"Share on Facebook\" border=\"0\" src=\"/style/2015/share_facebook.gif\" title=\"Share on Facebook\"/></a>\u00a0\u00a0<a href=\"http://twitter.com/intent/tweet?url=http%3A%2F%2Fwww.svastara.com%2Fmuzika%2F%3Ftekst%3D6200\"><img alt=\"Share on Twitter\" border=\"0\" src=\"/style/2015/share_twitter.gif\" title=\"Share on Twitter\"/></a>\u00a0\u00a0<a href=\"mailto:?subject=Flare - Waiting tekst&amp;body=http%3A%2F%2Fwww.svastara.com%2Fmuzika%2F%3Ftekst%3D6200\"><img alt=\"Share by e-mail\" border=\"0\" src=\"/style/2015/share_email.gif\" title=\"Share by e-mail\"/></a>\n</div>\n<br/><img src=\"/style/2015/line_green.png\"/>\n<br/>\n<br/><div class=\"sidelist_header\">Popularni tekstovi</div><a href=\"?tekst=6201\" id=\"sidelist\">Srebrni</a><a href=\"?tekst=10667\" id=\"sidelist\">Zaista</a><a href=\"?tekst=6206\" id=\"sidelist\">Dimom u o\u010di</a><a href=\"?tekst=9673\" id=\"sidelist\">Poslednja zelja</a><a href=\"?tekst=6205\" id=\"sidelist\">More</a><a href=\"?tekst=6204\" id=\"sidelist\">Nova doza</a><a href=\"?tekst=6203\" id=\"sidelist\">Ostajem jaka</a></div></div>\n</div>\n</div>]"
        },
        {
            "url": "?tekst=10667",
            "title": "Zaista",
            "lyrics": "[<div id=\"content-right\">\n<div id=\"content-padding\">\n<b><a href=\"?izvodjac=455\">Flare</a> - Zaista</b><br/>\n<br/>Opusti se.. ja sam vjetar<br/>Koji ti donosi.. svjezi zrak<br/>Jucer sam se pretvorila... u bjeli oblak<br/>Spajala kapljice.. koje padaju na tvoje lice<br/><br/>Otvorio si prozore i pogledao prema suncu<br/>Udahnuo duboko.. i kihnuo potiho..<br/>I gldao me ravno u oci.. te se nasmjesio..<br/>Gledao me ravno u oci.. pa me upitao<br/><br/>\"Tko si ti zaista???\"<br/>\"Ja sam vjetar stotina idila,<br/>Ti budi ptica koja vratit ce mi mir\"<br/><br/>Tako sam umorna <br/>Od trazenja ljubavi<br/>U ovoj sumi..<br/>Pet tona celika samo rijetki snivaju<br/>Zaista....<br/><br/>Zaista.. to je carolija<br/>Kad osmjeh tvoj me doziva,<br/>U sutone i svitanja<br/>To je moja utjeha<br/>Zaista bit cu tvoj Ram sa tisucu svjeca<br/>Da te griju dok si sam<br/><br/>\"Ja sam vjetar stotina idila,<br/>Ti budi ptica koja vratit ce mi mir.\"(2x)<br/><br/>Tako sam umorna <br/>Od trazenja ljubavi<br/>U ovoj sumi..<br/>Pet tona celika samo rijetki snivaju<br/>Zaista....<br/><br/><font color=\"green\"><i>- hvala funny-ivy</i></font><br/><br/><br/><div style=\"float: none; display: inline-block;\">\n<div id=\"extra\">\n<div style=\"float: none; display: inline-block;\">\n\t\t\t\tPodelite:<br/><a href=\"http://www.facebook.com/sharer.php?u=http%3A%2F%2Fwww.svastara.com%2Fmuzika%2F%3Ftekst%3D10667\"><img alt=\"Share on Facebook\" border=\"0\" src=\"/style/2015/share_facebook.gif\" title=\"Share on Facebook\"/></a>\u00a0\u00a0<a href=\"http://twitter.com/intent/tweet?url=http%3A%2F%2Fwww.svastara.com%2Fmuzika%2F%3Ftekst%3D10667\"><img alt=\"Share on Twitter\" border=\"0\" src=\"/style/2015/share_twitter.gif\" title=\"Share on Twitter\"/></a>\u00a0\u00a0<a href=\"mailto:?subject=Flare - Zaista tekst&amp;body=http%3A%2F%2Fwww.svastara.com%2Fmuzika%2F%3Ftekst%3D10667\"><img alt=\"Share by e-mail\" border=\"0\" src=\"/style/2015/share_email.gif\" title=\"Share by e-mail\"/></a>\n</div>\n<br/><img src=\"/style/2015/line_green.png\"/>\n<br/>\n<br/><div class=\"sidelist_header\">Popularni tekstovi</div><a href=\"?tekst=6201\" id=\"sidelist\">Srebrni</a><a href=\"?tekst=10667\" id=\"sidelist\">Zaista</a><a href=\"?tekst=6206\" id=\"sidelist\">Dimom u o\u010di</a><a href=\"?tekst=9673\" id=\"sidelist\">Poslednja zelja</a><a href=\"?tekst=6205\" id=\"sidelist\">More</a><a href=\"?tekst=6204\" id=\"sidelist\">Nova doza</a><a href=\"?tekst=6203\" id=\"sidelist\">Ostajem jaka</a></div>\n<div id=\"extra\">\n<script async=\"\" src=\"//pagead2.googlesyndication.com/pagead/js/adsbygoogle.js\"></script>\n<!-- sv-muz-tekst-300x250 -->\n<ins class=\"adsbygoogle\" data-ad-client=\"ca-pub-7280186603976417\" data-ad-slot=\"4744088596\" style=\"display:inline-block;width:300px;height:250px\"></ins>\n<script>\n\t\t\t\t(adsbygoogle = window.adsbygoogle || []).push({});\n\t\t\t\t</script>\n</div></div>\n</div>\n</div>]"
        }
    ]
}