{
    "Massimo Savi\u0107": [
        {
            "url": "?tekst=21014",
            "title": " Indija",
            "lyrics": "[<div id=\"content-right\">\n<div id=\"content-padding\">\n<b><a href=\"?izvodjac=202\">Massimo Savi\u0107</a> -  Indija</b><br/>\n<br/>Indija u zraku,<br/>inces miri\u0161e u mraku,<br/>\u010dujem vjetar kako sti\u017ee,<br/>mazi me po vratu.<br/>Milo dok te gledam,<br/>vidim ti dva lica,<br/>na tren si kao kurva,<br/>na tren kao djevica.<br/>Na krevetu je svila,<br/>od u\u017eitka sva se topi,<br/>kao oblaci pod nama,<br/>mi letimo po sobi,<br/>pripijen sam uz tebe,<br/>od vatre sve me zebe,<br/>malo me je strah,<br/>jer bojim se sam sebe (moja).<br/><br/>Ref: <br/>Bi\u0107e\u0161 uvjek moja,<br/>kad sje\u0107anja dogore,<br/>i godine se zbroje,<br/>a kad sklopim o\u010di,<br/>k`o an\u0111eo \u0107e\u0161 do\u0107i...<br/><br/>Indija u zraku,<br/>inces mirise u mraku,<br/>\u010dujem vjetar kako sti\u017ee,<br/>mazi me po vratu,<br/>htio bih da zna\u0161,<br/>da \u0107u tvoje snove hranit,<br/>kao vojnik hrabro,<br/>vje\u010dno \u0107u te branit.<br/>Sa usana \u0107u tvojih,<br/>\u010ditat pri\u010du svog \u017eivota,<br/>i ne\u0107e biti boli,<br/>la\u017ei ni sramota,<br/>budi za me tu,<br/>budi za me \u010dista,<br/>i kad bude\u0161 stara,<br/>meni bi\u0107e\u0161 ista (moja).<br/><br/>Ref: <br/>Bi\u0107e\u0161 uvjek moja,<br/>kad sje\u0107anja dogore,<br/>i godine se zbroje,<br/>a kad sklopim o\u010di,<br/>k`o an\u0111eo \u0107e\u0161 do\u0107i...<br/><br/><font color=\"green\"><i>- hvala Apostol</i></font><br/><br/><div style=\"float: none; display: inline-block;\">\n<div style=\"display: inline-block; width: 468px; float: left; margin: 5px 5px 0px 0px; padding: 5px;\">\n<script async=\"\" src=\"//pagead2.googlesyndication.com/pagead/js/adsbygoogle.js\"></script>\n<!-- sv-muz-tekst-468x60 -->\n<ins class=\"adsbygoogle\" data-ad-client=\"ca-pub-7280186603976417\" data-ad-slot=\"4469454054\" style=\"display:inline-block;width:468px;height:60px\"></ins>\n<script>\n\t\t\t\t(adsbygoogle = window.adsbygoogle || []).push({});\n\t\t\t\t</script>\n</div>\n<div id=\"extra\">\n<div style=\"float: none; display: inline-block;\">\n\t\t\t\tPodelite:<br/><a href=\"http://www.facebook.com/sharer.php?u=http%3A%2F%2Fwww.svastara.com%2Fmuzika%2F%3Ftekst%3D21014\"><img alt=\"Share on Facebook\" border=\"0\" src=\"/style/2015/share_facebook.gif\" title=\"Share on Facebook\"/></a>\u00a0\u00a0<a href=\"http://twitter.com/intent/tweet?url=http%3A%2F%2Fwww.svastara.com%2Fmuzika%2F%3Ftekst%3D21014\"><img alt=\"Share on Twitter\" border=\"0\" src=\"/style/2015/share_twitter.gif\" title=\"Share on Twitter\"/></a>\u00a0\u00a0<a href=\"mailto:?subject=Massimo Savi\u0107 -  Indija tekst&amp;body=http%3A%2F%2Fwww.svastara.com%2Fmuzika%2F%3Ftekst%3D21014\"><img alt=\"Share by e-mail\" border=\"0\" src=\"/style/2015/share_email.gif\" title=\"Share by e-mail\"/></a>\n</div>\n<br/><img src=\"/style/2015/line_green.png\"/>\n<br/>\n<br/><div class=\"sidelist_header\">Popularni tekstovi</div><a href=\"?tekst=3068\" id=\"sidelist\">Stranac u no\u0107i</a><a href=\"?tekst=10390\" id=\"sidelist\">Odjednom</a><a href=\"?tekst=15102\" id=\"sidelist\">Karta devera</a><a href=\"?tekst=14824\" id=\"sidelist\">Da mogu</a><a href=\"?tekst=3067\" id=\"sidelist\">Sunce sija, trava miri\u0161e</a><a href=\"?tekst=11379\" id=\"sidelist\">Kad \u010dovjek voli \u017eenu</a><a href=\"?tekst=15544\" id=\"sidelist\">Benzina</a></div></div>\n</div>\n</div>]"
        },
        {
            "url": "?tekst=15544",
            "title": "Benzina",
            "lyrics": "[<div id=\"content-right\">\n<div id=\"content-padding\">\n<b><a href=\"?izvodjac=202\">Massimo Savi\u0107</a> - Benzina</b><br/>\n<br/>Bio sam joj odan<br/>privrzen k\u2019o pseto<br/>pod prozorom stalno<br/>njezinim sam seto<br/><br/>I jos imam noge sve u hanzaplastu da, da<br/>skidala se gola iza vrazjeg stakla<br/>siluetu sam naziro kad bi se makla<br/>i bacala rublje po parketu<br/><br/>Pratijo sam ja nju<br/>kao bivsa ozna<br/>ona se pravila k\u2019o<br/>da me ne pozna<br/><br/>Samo je za sobom ostavljala miris<br/>ah taj miris to je cista rikavela<br/>skidala je rublje, ma to nije rublje<br/>to je bio desnak na Okinavu<br/><br/>REFREN<br/>Ti si moja benzina<br/>hajde da se volimo<br/>jer meni treba kerozina<br/>budi moje gorivo<br/>srce mi je tuklo kao ringo star<br/>mogu li vas za ples zamoliti bar<br/>ti si moja benzina<br/>hajde da se volimo<br/><br/>REFREN 2x<br/><br/><font color=\"green\"><i>- hvala Linda</i></font><br/><br/><div style=\"float: none; display: inline-block;\">\n<div style=\"display: inline-block; width: 468px; float: left; margin: 5px 5px 0px 0px; padding: 5px;\">\n<script async=\"\" src=\"//pagead2.googlesyndication.com/pagead/js/adsbygoogle.js\"></script>\n<!-- sv-muz-tekst-468x60 -->\n<ins class=\"adsbygoogle\" data-ad-client=\"ca-pub-7280186603976417\" data-ad-slot=\"4469454054\" style=\"display:inline-block;width:468px;height:60px\"></ins>\n<script>\n\t\t\t\t(adsbygoogle = window.adsbygoogle || []).push({});\n\t\t\t\t</script>\n</div>\n<div id=\"extra\">\n<div style=\"float: none; display: inline-block;\">\n\t\t\t\tPodelite:<br/><a href=\"http://www.facebook.com/sharer.php?u=http%3A%2F%2Fwww.svastara.com%2Fmuzika%2F%3Ftekst%3D15544\"><img alt=\"Share on Facebook\" border=\"0\" src=\"/style/2015/share_facebook.gif\" title=\"Share on Facebook\"/></a>\u00a0\u00a0<a href=\"http://twitter.com/intent/tweet?url=http%3A%2F%2Fwww.svastara.com%2Fmuzika%2F%3Ftekst%3D15544\"><img alt=\"Share on Twitter\" border=\"0\" src=\"/style/2015/share_twitter.gif\" title=\"Share on Twitter\"/></a>\u00a0\u00a0<a href=\"mailto:?subject=Massimo Savi\u0107 - Benzina tekst&amp;body=http%3A%2F%2Fwww.svastara.com%2Fmuzika%2F%3Ftekst%3D15544\"><img alt=\"Share by e-mail\" border=\"0\" src=\"/style/2015/share_email.gif\" title=\"Share by e-mail\"/></a>\n</div>\n<br/><img src=\"/style/2015/line_green.png\"/>\n<br/>\n<br/><div class=\"sidelist_header\">Popularni tekstovi</div><a href=\"?tekst=3068\" id=\"sidelist\">Stranac u no\u0107i</a><a href=\"?tekst=10390\" id=\"sidelist\">Odjednom</a><a href=\"?tekst=15102\" id=\"sidelist\">Karta devera</a><a href=\"?tekst=14824\" id=\"sidelist\">Da mogu</a><a href=\"?tekst=3067\" id=\"sidelist\">Sunce sija, trava miri\u0161e</a><a href=\"?tekst=11379\" id=\"sidelist\">Kad \u010dovjek voli \u017eenu</a><a href=\"?tekst=15544\" id=\"sidelist\">Benzina</a></div></div>\n</div>\n</div>]"
        },
        {
            "url": "?tekst=11616",
            "title": "Crni snjegovi",
            "lyrics": "[<div id=\"content-right\">\n<div id=\"content-padding\">\n<b><a href=\"?izvodjac=202\">Massimo Savi\u0107</a> - Crni snjegovi</b><br/>\n<br/>Nocas mislim na tebe<br/>i zovem te, <br/>glasovi su nestali.<br/>Stojim sam pod zvijezdama <br/>i pitam se<br/>kuda su te odveli.<br/>Jedna suza zna na mom obrazu<br/>losi smo vojnici skloni porazu.<br/><br/>Nocas padaju crni snjegovi,<br/>padaju da zaboravim,<br/>da ne osjetim bol u dugim nocima,<br/>da ne izgubim sjaj u tamnim ocima.<br/><br/>Nocas mislim na tebe<br/>i trazim te<br/>slika se izgubila.<br/>Jedna suza zna na mom obrazu<br/>losi smo vojnici skloni porazu.<br/><br/><font color=\"green\"><i>- hvala Any</i></font><br/><br/><div style=\"float: none; display: inline-block;\">\n<div style=\"display: inline-block; width: 468px; float: left; margin: 5px 5px 0px 0px; padding: 5px;\">\n<script async=\"\" src=\"//pagead2.googlesyndication.com/pagead/js/adsbygoogle.js\"></script>\n<!-- sv-muz-tekst-468x60 -->\n<ins class=\"adsbygoogle\" data-ad-client=\"ca-pub-7280186603976417\" data-ad-slot=\"4469454054\" style=\"display:inline-block;width:468px;height:60px\"></ins>\n<script>\n\t\t\t\t(adsbygoogle = window.adsbygoogle || []).push({});\n\t\t\t\t</script>\n</div>\n<div id=\"extra\">\n<div style=\"float: none; display: inline-block;\">\n\t\t\t\tPodelite:<br/><a href=\"http://www.facebook.com/sharer.php?u=http%3A%2F%2Fwww.svastara.com%2Fmuzika%2F%3Ftekst%3D11616\"><img alt=\"Share on Facebook\" border=\"0\" src=\"/style/2015/share_facebook.gif\" title=\"Share on Facebook\"/></a>\u00a0\u00a0<a href=\"http://twitter.com/intent/tweet?url=http%3A%2F%2Fwww.svastara.com%2Fmuzika%2F%3Ftekst%3D11616\"><img alt=\"Share on Twitter\" border=\"0\" src=\"/style/2015/share_twitter.gif\" title=\"Share on Twitter\"/></a>\u00a0\u00a0<a href=\"mailto:?subject=Massimo Savi\u0107 - Crni snjegovi tekst&amp;body=http%3A%2F%2Fwww.svastara.com%2Fmuzika%2F%3Ftekst%3D11616\"><img alt=\"Share by e-mail\" border=\"0\" src=\"/style/2015/share_email.gif\" title=\"Share by e-mail\"/></a>\n</div>\n<br/><img src=\"/style/2015/line_green.png\"/>\n<br/>\n<br/><div class=\"sidelist_header\">Popularni tekstovi</div><a href=\"?tekst=3068\" id=\"sidelist\">Stranac u no\u0107i</a><a href=\"?tekst=10390\" id=\"sidelist\">Odjednom</a><a href=\"?tekst=15102\" id=\"sidelist\">Karta devera</a><a href=\"?tekst=14824\" id=\"sidelist\">Da mogu</a><a href=\"?tekst=3067\" id=\"sidelist\">Sunce sija, trava miri\u0161e</a><a href=\"?tekst=11379\" id=\"sidelist\">Kad \u010dovjek voli \u017eenu</a><a href=\"?tekst=15544\" id=\"sidelist\">Benzina</a></div></div>\n</div>\n</div>]"
        },
        {
            "url": "?tekst=14824",
            "title": "Da mogu",
            "lyrics": "[<div id=\"content-right\">\n<div id=\"content-padding\">\n<b><a href=\"?izvodjac=202\">Massimo Savi\u0107</a> - Da mogu</b><br/>\n<br/>Probuditi stari sjaj<br/>i znati ponovo preci prag,<br/>odgoditi skori kraj<br/>i biti ponovo tebi drag<br/>i naci siguran stari trag,<br/>biti andjeo i biit vrag,<br/>da mogu<br/><br/>Uljepsao tvoj bih dan<br/>i za se nasao bolji put<br/>i suze pustio na tvoj dlan,<br/>a tvojom njeznoscu ogrnut,<br/>i da me zaspe u isti mah<br/>sa tvojh usana zlatni prah<br/>da mogu..<br/><br/>Odabrao bih pravi cas<br/>u tvome poljupcu je za me spas<br/>da mogu<br/><br/>Vratio i sebi cast<br/>oborio losu vlast<br/>al jos ne mogu<br/><br/>Bila bi zauvjek uz mene<br/>jesam li star za promjene<br/>prestar za takvo sto<br/>ostavti polu svjet<br/>ne traziti vise zlo<br/>a sposoban za novi let<br/>da mogu..<br/><br/>Pa ipak...<br/><br/><font color=\"green\"><i>- hvala Limit</i></font><br/><br/><br/><div style=\"float: none; display: inline-block;\">\n<div id=\"extra\">\n<div style=\"float: none; display: inline-block;\">\n\t\t\t\tPodelite:<br/><a href=\"http://www.facebook.com/sharer.php?u=http%3A%2F%2Fwww.svastara.com%2Fmuzika%2F%3Ftekst%3D14824\"><img alt=\"Share on Facebook\" border=\"0\" src=\"/style/2015/share_facebook.gif\" title=\"Share on Facebook\"/></a>\u00a0\u00a0<a href=\"http://twitter.com/intent/tweet?url=http%3A%2F%2Fwww.svastara.com%2Fmuzika%2F%3Ftekst%3D14824\"><img alt=\"Share on Twitter\" border=\"0\" src=\"/style/2015/share_twitter.gif\" title=\"Share on Twitter\"/></a>\u00a0\u00a0<a href=\"mailto:?subject=Massimo Savi\u0107 - Da mogu tekst&amp;body=http%3A%2F%2Fwww.svastara.com%2Fmuzika%2F%3Ftekst%3D14824\"><img alt=\"Share by e-mail\" border=\"0\" src=\"/style/2015/share_email.gif\" title=\"Share by e-mail\"/></a>\n</div>\n<br/><img src=\"/style/2015/line_green.png\"/>\n<br/>\n<br/><div class=\"sidelist_header\">Popularni tekstovi</div><a href=\"?tekst=3068\" id=\"sidelist\">Stranac u no\u0107i</a><a href=\"?tekst=10390\" id=\"sidelist\">Odjednom</a><a href=\"?tekst=15102\" id=\"sidelist\">Karta devera</a><a href=\"?tekst=14824\" id=\"sidelist\">Da mogu</a><a href=\"?tekst=3067\" id=\"sidelist\">Sunce sija, trava miri\u0161e</a><a href=\"?tekst=11379\" id=\"sidelist\">Kad \u010dovjek voli \u017eenu</a><a href=\"?tekst=15544\" id=\"sidelist\">Benzina</a></div>\n<div id=\"extra\">\n<script async=\"\" src=\"//pagead2.googlesyndication.com/pagead/js/adsbygoogle.js\"></script>\n<!-- sv-muz-tekst-300x250 -->\n<ins class=\"adsbygoogle\" data-ad-client=\"ca-pub-7280186603976417\" data-ad-slot=\"4744088596\" style=\"display:inline-block;width:300px;height:250px\"></ins>\n<script>\n\t\t\t\t(adsbygoogle = window.adsbygoogle || []).push({});\n\t\t\t\t</script>\n</div></div>\n</div>\n</div>]"
        },
        {
            "url": "?tekst=21593",
            "title": "Indija",
            "lyrics": "[<div id=\"content-right\">\n<div id=\"content-padding\">\n<b><a href=\"?izvodjac=202\">Massimo Savi\u0107</a> - Indija</b><br/>\n<br/>Indija u zraku, inces miri\u0161e u mraku<br/>\u010cujem vjetar kako sti\u017ee, mazi me po vratu<br/>Milo dok te gledam, vidim ti dva lica<br/>Na tren si kao kurva, na tren k'o djevica<br/><br/>Na krevetu je svila, od u\u017eitka sva se topi<br/>K'o oblaci  pod nama, mi letimo po sobi<br/>Pripijen sam uz tebe, od vatre sve me zebe<br/>Malo me je strah jer bojim se sam sebe<br/><br/>Refren:<br/><br/>Moja<br/>Bit \u0107e\u0161 uvijek moja<br/>Kad sje\u0107anja dogore<br/>I godine se zbroje<br/>A kad sklopim o\u010di k'o an\u0111eo \u0107e\u0161 do\u0107i<br/><br/>Indija u zraku, inces miri\u0161e u mraku<br/>\u010cujem vjetar kako sti\u017ee, mazi me po vratu<br/>Htio bi da zna\u0161 da \u0107u tvoje snove hranit<br/>Kao vojnik hrabro vje\u010dno \u0107u te branit<br/><br/>Sa usana \u0107u tvojih \u010ditat pri\u010du svog \u017eivota<br/>Ali ne\u0107e biti boli, la\u017ei ni sramota<br/>Budi za me tu, budi za me \u010dista<br/>I kad bude\u0161 stara meni bit \u0107e\u0161 ista<br/><br/>Moja..<br/><br/><font color=\"green\"><i>- hvala Marta S.</i></font><br/><br/><div style=\"float: none; display: inline-block;\">\n<div style=\"display: inline-block; width: 468px; float: left; margin: 5px 5px 0px 0px; padding: 5px;\">\n<script async=\"\" src=\"//pagead2.googlesyndication.com/pagead/js/adsbygoogle.js\"></script>\n<!-- sv-muz-tekst-468x60 -->\n<ins class=\"adsbygoogle\" data-ad-client=\"ca-pub-7280186603976417\" data-ad-slot=\"4469454054\" style=\"display:inline-block;width:468px;height:60px\"></ins>\n<script>\n\t\t\t\t(adsbygoogle = window.adsbygoogle || []).push({});\n\t\t\t\t</script>\n</div>\n<div id=\"extra\">\n<div style=\"float: none; display: inline-block;\">\n\t\t\t\tPodelite:<br/><a href=\"http://www.facebook.com/sharer.php?u=http%3A%2F%2Fwww.svastara.com%2Fmuzika%2F%3Ftekst%3D21593\"><img alt=\"Share on Facebook\" border=\"0\" src=\"/style/2015/share_facebook.gif\" title=\"Share on Facebook\"/></a>\u00a0\u00a0<a href=\"http://twitter.com/intent/tweet?url=http%3A%2F%2Fwww.svastara.com%2Fmuzika%2F%3Ftekst%3D21593\"><img alt=\"Share on Twitter\" border=\"0\" src=\"/style/2015/share_twitter.gif\" title=\"Share on Twitter\"/></a>\u00a0\u00a0<a href=\"mailto:?subject=Massimo Savi\u0107 - Indija tekst&amp;body=http%3A%2F%2Fwww.svastara.com%2Fmuzika%2F%3Ftekst%3D21593\"><img alt=\"Share by e-mail\" border=\"0\" src=\"/style/2015/share_email.gif\" title=\"Share by e-mail\"/></a>\n</div>\n<br/><img src=\"/style/2015/line_green.png\"/>\n<br/>\n<br/><div class=\"sidelist_header\">Popularni tekstovi</div><a href=\"?tekst=3068\" id=\"sidelist\">Stranac u no\u0107i</a><a href=\"?tekst=10390\" id=\"sidelist\">Odjednom</a><a href=\"?tekst=15102\" id=\"sidelist\">Karta devera</a><a href=\"?tekst=14824\" id=\"sidelist\">Da mogu</a><a href=\"?tekst=3067\" id=\"sidelist\">Sunce sija, trava miri\u0161e</a><a href=\"?tekst=11379\" id=\"sidelist\">Kad \u010dovjek voli \u017eenu</a><a href=\"?tekst=15544\" id=\"sidelist\">Benzina</a></div></div>\n</div>\n</div>]"
        },
        {
            "url": "?tekst=15115",
            "title": "Izdaleka",
            "lyrics": "[<div id=\"content-right\">\n<div id=\"content-padding\">\n<b><a href=\"?izvodjac=202\">Massimo Savi\u0107</a> - Izdaleka</b><br/>\n<br/>Nije vazno gdje si sad<br/>nije vazno s kim si vec<br/>ja jos uvijek imam za te jednu rijec<br/><br/>Meko ko kaplja kise<br/>tiho, od daha tise<br/>vrijeme ce reci sto ne mogu rijeci<br/>u srcu spoznat ces sve<br/><br/>Izdaleka, izdaleka jos te cuva ljubav neka<br/>izdaleka, izdaleka ljubim te u mislima<br/>prije budjenja i prije sna<br/><br/>Nije vazno da znam<br/>kako provodis dan<br/>uvijek bude sat kad mislis da si sam<br/><br/>Tad meko ko kaplja kise<br/>tiho, od daha tise<br/>vrijeme ce reci sto ne mogu rijeci<br/>u srcu ces spoznati sve<br/><br/><font color=\"green\"><i>- hvala Limit</i></font><br/><br/><div style=\"float: none; display: inline-block;\">\n<div style=\"display: inline-block; width: 468px; float: left; margin: 5px 5px 0px 0px; padding: 5px;\">\n<script async=\"\" src=\"//pagead2.googlesyndication.com/pagead/js/adsbygoogle.js\"></script>\n<!-- sv-muz-tekst-468x60 -->\n<ins class=\"adsbygoogle\" data-ad-client=\"ca-pub-7280186603976417\" data-ad-slot=\"4469454054\" style=\"display:inline-block;width:468px;height:60px\"></ins>\n<script>\n\t\t\t\t(adsbygoogle = window.adsbygoogle || []).push({});\n\t\t\t\t</script>\n</div>\n<div id=\"extra\">\n<div style=\"float: none; display: inline-block;\">\n\t\t\t\tPodelite:<br/><a href=\"http://www.facebook.com/sharer.php?u=http%3A%2F%2Fwww.svastara.com%2Fmuzika%2F%3Ftekst%3D15115\"><img alt=\"Share on Facebook\" border=\"0\" src=\"/style/2015/share_facebook.gif\" title=\"Share on Facebook\"/></a>\u00a0\u00a0<a href=\"http://twitter.com/intent/tweet?url=http%3A%2F%2Fwww.svastara.com%2Fmuzika%2F%3Ftekst%3D15115\"><img alt=\"Share on Twitter\" border=\"0\" src=\"/style/2015/share_twitter.gif\" title=\"Share on Twitter\"/></a>\u00a0\u00a0<a href=\"mailto:?subject=Massimo Savi\u0107 - Izdaleka tekst&amp;body=http%3A%2F%2Fwww.svastara.com%2Fmuzika%2F%3Ftekst%3D15115\"><img alt=\"Share by e-mail\" border=\"0\" src=\"/style/2015/share_email.gif\" title=\"Share by e-mail\"/></a>\n</div>\n<br/><img src=\"/style/2015/line_green.png\"/>\n<br/>\n<br/><div class=\"sidelist_header\">Popularni tekstovi</div><a href=\"?tekst=3068\" id=\"sidelist\">Stranac u no\u0107i</a><a href=\"?tekst=10390\" id=\"sidelist\">Odjednom</a><a href=\"?tekst=15102\" id=\"sidelist\">Karta devera</a><a href=\"?tekst=14824\" id=\"sidelist\">Da mogu</a><a href=\"?tekst=3067\" id=\"sidelist\">Sunce sija, trava miri\u0161e</a><a href=\"?tekst=11379\" id=\"sidelist\">Kad \u010dovjek voli \u017eenu</a><a href=\"?tekst=15544\" id=\"sidelist\">Benzina</a></div></div>\n</div>\n</div>]"
        },
        {
            "url": "?tekst=11379",
            "title": "Kad \u010dovjek voli \u017eenu",
            "lyrics": "[<div id=\"content-right\">\n<div id=\"content-padding\">\n<b><a href=\"?izvodjac=202\">Massimo Savi\u0107</a> - Kad \u010dovjek voli \u017eenu</b><br/>\n<br/>Za sve koji tu\u017ena lica lutaju kroz no\u0107<br/>Za sve one \u0161to ih sre\u0107a \u010desto vara<br/>Pjevam pjesmu da se vrati snaga, bol i mo\u0107<br/>Sada vjerujem da nebo \u010duda stvara<br/><br/>Kad nas vrijeme dijeli, kad nam uzme sve<br/>Samo moja ljubav uvijek ostaje, ljubav ostaje<br/><br/>Kad \u010dovjek voli \u017eenu<br/>On pobje\u0111uje sve<br/>Kad ljubav osjeti du\u0161om svom<br/>Jo\u0161 je ja\u010di zbog nje<br/><br/>Ima ljudi koji blijeda lica sanjaju bez sna<br/>Ima dana kad nas \u010dudan nemir slama<br/>Pjevam pjesmu da se vrati snaga, bol i mo\u0107<br/>Sada vjerujem da nebo \u010duda stvara<br/><br/>Kad nas vrijeme dijeli, kad nam uzme sve<br/>Samo moja ljubav uvijek ostaje, ljubav ostaje<br/><br/><font color=\"green\"><i>- hvala Joma</i></font><br/><br/><div style=\"float: none; display: inline-block;\">\n<div style=\"display: inline-block; width: 468px; float: left; margin: 5px 5px 0px 0px; padding: 5px;\">\n<script async=\"\" src=\"//pagead2.googlesyndication.com/pagead/js/adsbygoogle.js\"></script>\n<!-- sv-muz-tekst-468x60 -->\n<ins class=\"adsbygoogle\" data-ad-client=\"ca-pub-7280186603976417\" data-ad-slot=\"4469454054\" style=\"display:inline-block;width:468px;height:60px\"></ins>\n<script>\n\t\t\t\t(adsbygoogle = window.adsbygoogle || []).push({});\n\t\t\t\t</script>\n</div>\n<div id=\"extra\">\n<div style=\"float: none; display: inline-block;\">\n\t\t\t\tPodelite:<br/><a href=\"http://www.facebook.com/sharer.php?u=http%3A%2F%2Fwww.svastara.com%2Fmuzika%2F%3Ftekst%3D11379\"><img alt=\"Share on Facebook\" border=\"0\" src=\"/style/2015/share_facebook.gif\" title=\"Share on Facebook\"/></a>\u00a0\u00a0<a href=\"http://twitter.com/intent/tweet?url=http%3A%2F%2Fwww.svastara.com%2Fmuzika%2F%3Ftekst%3D11379\"><img alt=\"Share on Twitter\" border=\"0\" src=\"/style/2015/share_twitter.gif\" title=\"Share on Twitter\"/></a>\u00a0\u00a0<a href=\"mailto:?subject=Massimo Savi\u0107 - Kad \u010dovjek voli \u017eenu tekst&amp;body=http%3A%2F%2Fwww.svastara.com%2Fmuzika%2F%3Ftekst%3D11379\"><img alt=\"Share by e-mail\" border=\"0\" src=\"/style/2015/share_email.gif\" title=\"Share by e-mail\"/></a>\n</div>\n<br/><img src=\"/style/2015/line_green.png\"/>\n<br/>\n<br/><div class=\"sidelist_header\">Popularni tekstovi</div><a href=\"?tekst=3068\" id=\"sidelist\">Stranac u no\u0107i</a><a href=\"?tekst=10390\" id=\"sidelist\">Odjednom</a><a href=\"?tekst=15102\" id=\"sidelist\">Karta devera</a><a href=\"?tekst=14824\" id=\"sidelist\">Da mogu</a><a href=\"?tekst=3067\" id=\"sidelist\">Sunce sija, trava miri\u0161e</a><a href=\"?tekst=11379\" id=\"sidelist\">Kad \u010dovjek voli \u017eenu</a><a href=\"?tekst=15544\" id=\"sidelist\">Benzina</a></div></div>\n</div>\n</div>]"
        },
        {
            "url": "?tekst=15102",
            "title": "Karta devera",
            "lyrics": "[<div id=\"content-right\">\n<div id=\"content-padding\">\n<b><a href=\"?izvodjac=202\">Massimo Savi\u0107</a> - Karta devera</b><br/>\n<br/>Nista vise nije isto<br/>Otkada me ne volis<br/>Stol za dvoje, prazno misto<br/>Puno sporki pijati<br/>Nista vise nije isto, moja ljubavi<br/>Suha spiza, juto vino<br/>I jugo sto ne prolazi.<br/><br/>Nista vise nije isto<br/>Kuca se zapustila<br/>Vrt nam je obrijesta dracon<br/>Barka se utopila<br/>Prijatelji tu i tamo svrate u nas dom<br/>Donesu mi lipih rici <br/>I tugu, tugu za tobom<br/><br/>Karta devera,<br/>Karta devera<br/>Ostruga je zivot sve lipo iz mene <br/>Otkad te nema...<br/><br/>Nista vise nije isto, moja ljubavi<br/>Suha spiza, juto vino<br/>I jugo sto ne prolazi<br/>Prijateji tu i tamo svrate u moj dom<br/>Donesu mi lipih rici <br/>I tugu, tugu za tobom.<br/><br/>Karta devera,<br/>Karta devera<br/>Ostruga je zivot sve lipo iz mene <br/>Otkad te nema...<br/><br/>Karta devera, karta devera<br/>Karta devera<br/>Stala ferata na pola puta<br/>I daje mi nema<br/><br/><font color=\"green\"><i>- hvala zavrzlama</i></font><br/><br/><br/><div style=\"float: none; display: inline-block;\">\n<div id=\"extra\">\n<div style=\"float: none; display: inline-block;\">\n\t\t\t\tPodelite:<br/><a href=\"http://www.facebook.com/sharer.php?u=http%3A%2F%2Fwww.svastara.com%2Fmuzika%2F%3Ftekst%3D15102\"><img alt=\"Share on Facebook\" border=\"0\" src=\"/style/2015/share_facebook.gif\" title=\"Share on Facebook\"/></a>\u00a0\u00a0<a href=\"http://twitter.com/intent/tweet?url=http%3A%2F%2Fwww.svastara.com%2Fmuzika%2F%3Ftekst%3D15102\"><img alt=\"Share on Twitter\" border=\"0\" src=\"/style/2015/share_twitter.gif\" title=\"Share on Twitter\"/></a>\u00a0\u00a0<a href=\"mailto:?subject=Massimo Savi\u0107 - Karta devera tekst&amp;body=http%3A%2F%2Fwww.svastara.com%2Fmuzika%2F%3Ftekst%3D15102\"><img alt=\"Share by e-mail\" border=\"0\" src=\"/style/2015/share_email.gif\" title=\"Share by e-mail\"/></a>\n</div>\n<br/><img src=\"/style/2015/line_green.png\"/>\n<br/>\n<br/><div class=\"sidelist_header\">Popularni tekstovi</div><a href=\"?tekst=3068\" id=\"sidelist\">Stranac u no\u0107i</a><a href=\"?tekst=10390\" id=\"sidelist\">Odjednom</a><a href=\"?tekst=15102\" id=\"sidelist\">Karta devera</a><a href=\"?tekst=14824\" id=\"sidelist\">Da mogu</a><a href=\"?tekst=3067\" id=\"sidelist\">Sunce sija, trava miri\u0161e</a><a href=\"?tekst=11379\" id=\"sidelist\">Kad \u010dovjek voli \u017eenu</a><a href=\"?tekst=15544\" id=\"sidelist\">Benzina</a></div>\n<div id=\"extra\">\n<script async=\"\" src=\"//pagead2.googlesyndication.com/pagead/js/adsbygoogle.js\"></script>\n<!-- sv-muz-tekst-300x250 -->\n<ins class=\"adsbygoogle\" data-ad-client=\"ca-pub-7280186603976417\" data-ad-slot=\"4744088596\" style=\"display:inline-block;width:300px;height:250px\"></ins>\n<script>\n\t\t\t\t(adsbygoogle = window.adsbygoogle || []).push({});\n\t\t\t\t</script>\n</div></div>\n</div>\n</div>]"
        },
        {
            "url": "?tekst=15546",
            "title": "Kazu",
            "lyrics": "[<div id=\"content-right\">\n<div id=\"content-padding\">\n<b><a href=\"?izvodjac=202\">Massimo Savi\u0107</a> - Kazu</b><br/>\n<br/>Kazu neke casne zene<br/>kazu da nisi za mene<br/>kazu snjeg ce, srce zebe<br/>kazu da nisi za mene<br/>da nisam za tebe<br/><br/>REFREN<br/>Kuda si sve isla<br/>gdje si samo bila<br/>na izvoru gorkom<br/>lice si umila<br/><br/>Kuda je sve poslo<br/>tvoje slabo tijelo<br/>lose odjeveno<br/>za pice i jelo<br/><br/>Kazu neki casni ljudi<br/>kazu, pa uz mene budi<br/>kazu, a ja znam da lazu<br/><br/>REFREN<br/><br/>Kazu neki casni ljudi<br/>kazu, pa uz mene budi<br/>kazu, a ja znam da lazu<br/><br/><font color=\"green\"><i>- hvala Linda</i></font><br/><br/><div style=\"float: none; display: inline-block;\">\n<div style=\"display: inline-block; width: 468px; float: left; margin: 5px 5px 0px 0px; padding: 5px;\">\n<script async=\"\" src=\"//pagead2.googlesyndication.com/pagead/js/adsbygoogle.js\"></script>\n<!-- sv-muz-tekst-468x60 -->\n<ins class=\"adsbygoogle\" data-ad-client=\"ca-pub-7280186603976417\" data-ad-slot=\"4469454054\" style=\"display:inline-block;width:468px;height:60px\"></ins>\n<script>\n\t\t\t\t(adsbygoogle = window.adsbygoogle || []).push({});\n\t\t\t\t</script>\n</div>\n<div id=\"extra\">\n<div style=\"float: none; display: inline-block;\">\n\t\t\t\tPodelite:<br/><a href=\"http://www.facebook.com/sharer.php?u=http%3A%2F%2Fwww.svastara.com%2Fmuzika%2F%3Ftekst%3D15546\"><img alt=\"Share on Facebook\" border=\"0\" src=\"/style/2015/share_facebook.gif\" title=\"Share on Facebook\"/></a>\u00a0\u00a0<a href=\"http://twitter.com/intent/tweet?url=http%3A%2F%2Fwww.svastara.com%2Fmuzika%2F%3Ftekst%3D15546\"><img alt=\"Share on Twitter\" border=\"0\" src=\"/style/2015/share_twitter.gif\" title=\"Share on Twitter\"/></a>\u00a0\u00a0<a href=\"mailto:?subject=Massimo Savi\u0107 - Kazu tekst&amp;body=http%3A%2F%2Fwww.svastara.com%2Fmuzika%2F%3Ftekst%3D15546\"><img alt=\"Share by e-mail\" border=\"0\" src=\"/style/2015/share_email.gif\" title=\"Share by e-mail\"/></a>\n</div>\n<br/><img src=\"/style/2015/line_green.png\"/>\n<br/>\n<br/><div class=\"sidelist_header\">Popularni tekstovi</div><a href=\"?tekst=3068\" id=\"sidelist\">Stranac u no\u0107i</a><a href=\"?tekst=10390\" id=\"sidelist\">Odjednom</a><a href=\"?tekst=15102\" id=\"sidelist\">Karta devera</a><a href=\"?tekst=14824\" id=\"sidelist\">Da mogu</a><a href=\"?tekst=3067\" id=\"sidelist\">Sunce sija, trava miri\u0161e</a><a href=\"?tekst=11379\" id=\"sidelist\">Kad \u010dovjek voli \u017eenu</a><a href=\"?tekst=15544\" id=\"sidelist\">Benzina</a></div></div>\n</div>\n</div>]"
        },
        {
            "url": "?tekst=16221",
            "title": "Libar",
            "lyrics": "[<div id=\"content-right\">\n<div id=\"content-padding\">\n<b><a href=\"?izvodjac=202\">Massimo Savi\u0107</a> - Libar</b><br/>\n<br/>U libar svojih dugova,<br/>upisi mene,<br/>jer odavno te kupujem,<br/>sa onim sta si htela cut,<br/>od straha da ne potone,<br/>tvoja ljubav za mene,<br/>kao cela u snici caja,<br/>dok drzi dah,<br/>ja nemam razloga za strah.<br/><br/>ref:<br/>Dajem ti vese i note,<br/>sve moje sare ne perle na dah,<br/>jos te mogu pesmom kupiti,<br/>lukavo i slatko recivo,<br/>i jos uvek mogu ti podvaliti,<br/>LJUBAV!<br/><br/>I seve cu ti obecati,<br/>i bas sve sto hoces,<br/>moju kozu moju kost,<br/>i lice koje pozelis,<br/>od straha da ne potone,<br/>tvoja ljubav za mene,<br/>kao cela u snici caja,<br/>dok drzi dah,<br/>ja nemam razloga za strah.<br/><br/>ref:Dajem ti vese i note,<br/>sve moje sare ne perle na dah,<br/>jos te mogu pesmom kupiti,<br/>lukavo i slatko recivo,<br/>i jos uvek mogu ti podvaliti,<br/>LJUBAV!Lubav!...(2x)<br/><br/><font color=\"green\"><i>- hvala Kica</i></font><br/><br/><div style=\"float: none; display: inline-block;\">\n<div style=\"display: inline-block; width: 468px; float: left; margin: 5px 5px 0px 0px; padding: 5px;\">\n<script async=\"\" src=\"//pagead2.googlesyndication.com/pagead/js/adsbygoogle.js\"></script>\n<!-- sv-muz-tekst-468x60 -->\n<ins class=\"adsbygoogle\" data-ad-client=\"ca-pub-7280186603976417\" data-ad-slot=\"4469454054\" style=\"display:inline-block;width:468px;height:60px\"></ins>\n<script>\n\t\t\t\t(adsbygoogle = window.adsbygoogle || []).push({});\n\t\t\t\t</script>\n</div>\n<div id=\"extra\">\n<div style=\"float: none; display: inline-block;\">\n\t\t\t\tPodelite:<br/><a href=\"http://www.facebook.com/sharer.php?u=http%3A%2F%2Fwww.svastara.com%2Fmuzika%2F%3Ftekst%3D16221\"><img alt=\"Share on Facebook\" border=\"0\" src=\"/style/2015/share_facebook.gif\" title=\"Share on Facebook\"/></a>\u00a0\u00a0<a href=\"http://twitter.com/intent/tweet?url=http%3A%2F%2Fwww.svastara.com%2Fmuzika%2F%3Ftekst%3D16221\"><img alt=\"Share on Twitter\" border=\"0\" src=\"/style/2015/share_twitter.gif\" title=\"Share on Twitter\"/></a>\u00a0\u00a0<a href=\"mailto:?subject=Massimo Savi\u0107 - Libar tekst&amp;body=http%3A%2F%2Fwww.svastara.com%2Fmuzika%2F%3Ftekst%3D16221\"><img alt=\"Share by e-mail\" border=\"0\" src=\"/style/2015/share_email.gif\" title=\"Share by e-mail\"/></a>\n</div>\n<br/><img src=\"/style/2015/line_green.png\"/>\n<br/>\n<br/><div class=\"sidelist_header\">Popularni tekstovi</div><a href=\"?tekst=3068\" id=\"sidelist\">Stranac u no\u0107i</a><a href=\"?tekst=10390\" id=\"sidelist\">Odjednom</a><a href=\"?tekst=15102\" id=\"sidelist\">Karta devera</a><a href=\"?tekst=14824\" id=\"sidelist\">Da mogu</a><a href=\"?tekst=3067\" id=\"sidelist\">Sunce sija, trava miri\u0161e</a><a href=\"?tekst=11379\" id=\"sidelist\">Kad \u010dovjek voli \u017eenu</a><a href=\"?tekst=15544\" id=\"sidelist\">Benzina</a></div></div>\n</div>\n</div>]"
        },
        {
            "url": "?tekst=21592",
            "title": "Ljubav",
            "lyrics": "[<div id=\"content-right\">\n<div id=\"content-padding\">\n<b><a href=\"?izvodjac=202\">Massimo Savi\u0107</a> - Ljubav</b><br/>\n<br/>Po\u010dinje tiho, po\u010dinje plaho<br/>Al' po\u010dinje<br/>Po\u010dinje glupo, po\u010dinje kradom<br/>Tako po\u010dne <br/>I onda<br/>Uzme te za vrat <br/>I onda <br/>Vi\u010de na sav glas<br/>Odjednom si na nogama<br/>A sanja\u0161,<br/>Sanja\u0161, sanja\u0161<br/>Misli\u0161 da ne\u0107e,<br/>Ne, nije ni blizu, <br/>Pro\u0107i \u0107e<br/>Nije to ni\u0161ta,<br/>Samo prolazi\u0161 kroz krizu<br/>Uz malo sre\u0107e prestat \u0107e<br/>Al' onda primi te za vrat<br/>I onda vi\u010de na sav glas<br/>Odjednom si na nogama<br/>A sanja\u0161,<br/>Sanja\u0161, sanja\u0161<br/>Dok ka\u017ee\u0161 sebi:<br/> \"To nije dobro, <br/>to treba izvaditi s korijenom\"<br/>Dok ka\u017ee\u0161 sebi: <br/>\"Tu treba stati,<br/>jo\u0161 je stanje ubrojivo\"<br/>Ona izmi\u010de ti pod,<br/>Ona tek dodaje glas<br/>Odjednom si na krilima<br/>I sanja\u0161,<br/>Sanja\u0161, sanja\u0161<br/><br/><font color=\"green\"><i>- hvala Marta S.</i></font><br/><br/><div style=\"float: none; display: inline-block;\">\n<div style=\"display: inline-block; width: 468px; float: left; margin: 5px 5px 0px 0px; padding: 5px;\">\n<script async=\"\" src=\"//pagead2.googlesyndication.com/pagead/js/adsbygoogle.js\"></script>\n<!-- sv-muz-tekst-468x60 -->\n<ins class=\"adsbygoogle\" data-ad-client=\"ca-pub-7280186603976417\" data-ad-slot=\"4469454054\" style=\"display:inline-block;width:468px;height:60px\"></ins>\n<script>\n\t\t\t\t(adsbygoogle = window.adsbygoogle || []).push({});\n\t\t\t\t</script>\n</div>\n<div id=\"extra\">\n<div style=\"float: none; display: inline-block;\">\n\t\t\t\tPodelite:<br/><a href=\"http://www.facebook.com/sharer.php?u=http%3A%2F%2Fwww.svastara.com%2Fmuzika%2F%3Ftekst%3D21592\"><img alt=\"Share on Facebook\" border=\"0\" src=\"/style/2015/share_facebook.gif\" title=\"Share on Facebook\"/></a>\u00a0\u00a0<a href=\"http://twitter.com/intent/tweet?url=http%3A%2F%2Fwww.svastara.com%2Fmuzika%2F%3Ftekst%3D21592\"><img alt=\"Share on Twitter\" border=\"0\" src=\"/style/2015/share_twitter.gif\" title=\"Share on Twitter\"/></a>\u00a0\u00a0<a href=\"mailto:?subject=Massimo Savi\u0107 - Ljubav tekst&amp;body=http%3A%2F%2Fwww.svastara.com%2Fmuzika%2F%3Ftekst%3D21592\"><img alt=\"Share by e-mail\" border=\"0\" src=\"/style/2015/share_email.gif\" title=\"Share by e-mail\"/></a>\n</div>\n<br/><img src=\"/style/2015/line_green.png\"/>\n<br/>\n<br/><div class=\"sidelist_header\">Popularni tekstovi</div><a href=\"?tekst=3068\" id=\"sidelist\">Stranac u no\u0107i</a><a href=\"?tekst=10390\" id=\"sidelist\">Odjednom</a><a href=\"?tekst=15102\" id=\"sidelist\">Karta devera</a><a href=\"?tekst=14824\" id=\"sidelist\">Da mogu</a><a href=\"?tekst=3067\" id=\"sidelist\">Sunce sija, trava miri\u0161e</a><a href=\"?tekst=11379\" id=\"sidelist\">Kad \u010dovjek voli \u017eenu</a><a href=\"?tekst=15544\" id=\"sidelist\">Benzina</a></div></div>\n</div>\n</div>]"
        },
        {
            "url": "?tekst=21665",
            "title": "Moja voda",
            "lyrics": "[<div id=\"content-right\">\n<div id=\"content-padding\">\n<b><a href=\"?izvodjac=202\">Massimo Savi\u0107</a> - Moja voda</b><br/>\n<br/>Ostao sam sasvim sam da lezim na suncu,<br/>ja zvao sam te da dodjes iz snova,<br/>I pruzis mi ruku, <br/>ja molio sam da se napune moja mora I reke,<br/>u njima jos jednom da osetim nova ljubav da tece,<br/><br/>I pjevam,<br/>budi moja voda, ja sam sada vatra izgorjetcu, <br/>I kazem, <br/>proli se po meni, budi sve sto zelim ja zivjetcu<br/><br/>Ja znao sam da ces doci, doci I donjeti kisu,<br/>jer cekao sam kao suha zemlja kad ceka svoju vodu<br/><br/>Hvala, Che Guevara<br/><br/><font color=\"green\"><i>- hvala Che Guevara</i></font><br/><br/><br/><div style=\"float: none; display: inline-block;\">\n<div id=\"extra\">\n<div style=\"float: none; display: inline-block;\">\n\t\t\t\tPodelite:<br/><a href=\"http://www.facebook.com/sharer.php?u=http%3A%2F%2Fwww.svastara.com%2Fmuzika%2F%3Ftekst%3D21665\"><img alt=\"Share on Facebook\" border=\"0\" src=\"/style/2015/share_facebook.gif\" title=\"Share on Facebook\"/></a>\u00a0\u00a0<a href=\"http://twitter.com/intent/tweet?url=http%3A%2F%2Fwww.svastara.com%2Fmuzika%2F%3Ftekst%3D21665\"><img alt=\"Share on Twitter\" border=\"0\" src=\"/style/2015/share_twitter.gif\" title=\"Share on Twitter\"/></a>\u00a0\u00a0<a href=\"mailto:?subject=Massimo Savi\u0107 - Moja voda tekst&amp;body=http%3A%2F%2Fwww.svastara.com%2Fmuzika%2F%3Ftekst%3D21665\"><img alt=\"Share by e-mail\" border=\"0\" src=\"/style/2015/share_email.gif\" title=\"Share by e-mail\"/></a>\n</div>\n<br/><img src=\"/style/2015/line_green.png\"/>\n<br/>\n<br/><div class=\"sidelist_header\">Popularni tekstovi</div><a href=\"?tekst=3068\" id=\"sidelist\">Stranac u no\u0107i</a><a href=\"?tekst=10390\" id=\"sidelist\">Odjednom</a><a href=\"?tekst=15102\" id=\"sidelist\">Karta devera</a><a href=\"?tekst=14824\" id=\"sidelist\">Da mogu</a><a href=\"?tekst=3067\" id=\"sidelist\">Sunce sija, trava miri\u0161e</a><a href=\"?tekst=11379\" id=\"sidelist\">Kad \u010dovjek voli \u017eenu</a><a href=\"?tekst=15544\" id=\"sidelist\">Benzina</a></div>\n<div id=\"extra\">\n<script async=\"\" src=\"//pagead2.googlesyndication.com/pagead/js/adsbygoogle.js\"></script>\n<!-- sv-muz-tekst-300x250 -->\n<ins class=\"adsbygoogle\" data-ad-client=\"ca-pub-7280186603976417\" data-ad-slot=\"4744088596\" style=\"display:inline-block;width:300px;height:250px\"></ins>\n<script>\n\t\t\t\t(adsbygoogle = window.adsbygoogle || []).push({});\n\t\t\t\t</script>\n</div></div>\n</div>\n</div>]"
        },
        {
            "url": "?tekst=10390",
            "title": "Odjednom",
            "lyrics": "[<div id=\"content-right\">\n<div id=\"content-padding\">\n<b><a href=\"?izvodjac=202\">Massimo Savi\u0107</a> - Odjednom</b><br/>\n<br/>Mogu re\u0107i \u0161utnjom, mogu prstima<br/>I u pijesku stopama, i u mraku usnama<br/>Mogu \u010duti srcem, mogu o\u010dima<br/>Nekim novim mirisom, nekim novim okusom<br/>Zauvijek, promijenilo se sve<br/>Odjednom ti,<br/>U jutru \u0161to kraj mene drijema<br/>ti, <br/>a \u010dinilo se nikog nema,<br/>ti,<br/>odjednom ti u kapi ki\u0161e,<br/>ti, <br/>a \u010dinilo se nikad vi\u0161e<br/>Mogu vidjet ko\u017eu, mogu mislima<br/>To se samo dogodi, i bez rije\u010di pogodi<br/>Zauvijek, promijenilo se sve<br/>Odjednom ti,<br/>U jutru \u0161to kraj mene drijema<br/>ti, <br/>a \u010dinilo se nikog nema,<br/>ti,<br/>odjednom ti u kapi ki\u0161e,<br/>ti, <br/>a \u010dinilo se nikad vi\u0161e<br/>Skupilo se vrijeme,<br/>U jedan dan<br/>Dan u kom' se budim i osje\u0107am <br/>Odjednom ti,<br/>U jutru \u0161to kraj mene drijema<br/>ti, <br/>a \u010dinilo se nikog nema,<br/>ti,<br/>odjednom ti u kapi ki\u0161e,<br/>ti, <br/>a \u010dinilo se nikad vi\u0161e.<br/><br/><font color=\"green\"><i>- hvala Iron Maiden</i></font><br/><br/><br/><div style=\"float: none; display: inline-block;\">\n<div id=\"extra\">\n<div style=\"float: none; display: inline-block;\">\n\t\t\t\tPodelite:<br/><a href=\"http://www.facebook.com/sharer.php?u=http%3A%2F%2Fwww.svastara.com%2Fmuzika%2F%3Ftekst%3D10390\"><img alt=\"Share on Facebook\" border=\"0\" src=\"/style/2015/share_facebook.gif\" title=\"Share on Facebook\"/></a>\u00a0\u00a0<a href=\"http://twitter.com/intent/tweet?url=http%3A%2F%2Fwww.svastara.com%2Fmuzika%2F%3Ftekst%3D10390\"><img alt=\"Share on Twitter\" border=\"0\" src=\"/style/2015/share_twitter.gif\" title=\"Share on Twitter\"/></a>\u00a0\u00a0<a href=\"mailto:?subject=Massimo Savi\u0107 - Odjednom tekst&amp;body=http%3A%2F%2Fwww.svastara.com%2Fmuzika%2F%3Ftekst%3D10390\"><img alt=\"Share by e-mail\" border=\"0\" src=\"/style/2015/share_email.gif\" title=\"Share by e-mail\"/></a>\n</div>\n<br/><img src=\"/style/2015/line_green.png\"/>\n<br/>\n<br/><div class=\"sidelist_header\">Popularni tekstovi</div><a href=\"?tekst=3068\" id=\"sidelist\">Stranac u no\u0107i</a><a href=\"?tekst=10390\" id=\"sidelist\">Odjednom</a><a href=\"?tekst=15102\" id=\"sidelist\">Karta devera</a><a href=\"?tekst=14824\" id=\"sidelist\">Da mogu</a><a href=\"?tekst=3067\" id=\"sidelist\">Sunce sija, trava miri\u0161e</a><a href=\"?tekst=11379\" id=\"sidelist\">Kad \u010dovjek voli \u017eenu</a><a href=\"?tekst=15544\" id=\"sidelist\">Benzina</a></div>\n<div id=\"extra\">\n<script async=\"\" src=\"//pagead2.googlesyndication.com/pagead/js/adsbygoogle.js\"></script>\n<!-- sv-muz-tekst-300x250 -->\n<ins class=\"adsbygoogle\" data-ad-client=\"ca-pub-7280186603976417\" data-ad-slot=\"4744088596\" style=\"display:inline-block;width:300px;height:250px\"></ins>\n<script>\n\t\t\t\t(adsbygoogle = window.adsbygoogle || []).push({});\n\t\t\t\t</script>\n</div></div>\n</div>\n</div>]"
        },
        {
            "url": "?tekst=11617",
            "title": "Plavi andjeo",
            "lyrics": "[<div id=\"content-right\">\n<div id=\"content-padding\">\n<b><a href=\"?izvodjac=202\">Massimo Savi\u0107</a> - Plavi andjeo</b><br/>\n<br/>Tvoja mala soba<br/>kao plava kutija,<br/>vani hladna noc bez mjeseca.<br/>Srebro je na licu<br/>nocas zvijezda umire,<br/>a ja postojim samo za tebe.<br/><br/>Ne vjerujem rijecima,<br/>ti nisi iskrena<br/>osjecam toplinu<br/>i bol u ocima.<br/><br/>Vodi me, plavi adnjele<br/>srusio se svijet,<br/>vodi me da zaboravim na sve<br/>budi tu, kraj mene.<br/><br/>Vodi me da zaboravim na sve<br/>budi tu, andjele.<br/><br/><font color=\"green\"><i>- hvala Any</i></font><br/><br/><br/><div style=\"float: none; display: inline-block;\">\n<div id=\"extra\">\n<div style=\"float: none; display: inline-block;\">\n\t\t\t\tPodelite:<br/><a href=\"http://www.facebook.com/sharer.php?u=http%3A%2F%2Fwww.svastara.com%2Fmuzika%2F%3Ftekst%3D11617\"><img alt=\"Share on Facebook\" border=\"0\" src=\"/style/2015/share_facebook.gif\" title=\"Share on Facebook\"/></a>\u00a0\u00a0<a href=\"http://twitter.com/intent/tweet?url=http%3A%2F%2Fwww.svastara.com%2Fmuzika%2F%3Ftekst%3D11617\"><img alt=\"Share on Twitter\" border=\"0\" src=\"/style/2015/share_twitter.gif\" title=\"Share on Twitter\"/></a>\u00a0\u00a0<a href=\"mailto:?subject=Massimo Savi\u0107 - Plavi andjeo tekst&amp;body=http%3A%2F%2Fwww.svastara.com%2Fmuzika%2F%3Ftekst%3D11617\"><img alt=\"Share by e-mail\" border=\"0\" src=\"/style/2015/share_email.gif\" title=\"Share by e-mail\"/></a>\n</div>\n<br/><img src=\"/style/2015/line_green.png\"/>\n<br/>\n<br/><div class=\"sidelist_header\">Popularni tekstovi</div><a href=\"?tekst=3068\" id=\"sidelist\">Stranac u no\u0107i</a><a href=\"?tekst=10390\" id=\"sidelist\">Odjednom</a><a href=\"?tekst=15102\" id=\"sidelist\">Karta devera</a><a href=\"?tekst=14824\" id=\"sidelist\">Da mogu</a><a href=\"?tekst=3067\" id=\"sidelist\">Sunce sija, trava miri\u0161e</a><a href=\"?tekst=11379\" id=\"sidelist\">Kad \u010dovjek voli \u017eenu</a><a href=\"?tekst=15544\" id=\"sidelist\">Benzina</a></div>\n<div id=\"extra\">\n<script async=\"\" src=\"//pagead2.googlesyndication.com/pagead/js/adsbygoogle.js\"></script>\n<!-- sv-muz-tekst-300x250 -->\n<ins class=\"adsbygoogle\" data-ad-client=\"ca-pub-7280186603976417\" data-ad-slot=\"4744088596\" style=\"display:inline-block;width:300px;height:250px\"></ins>\n<script>\n\t\t\t\t(adsbygoogle = window.adsbygoogle || []).push({});\n\t\t\t\t</script>\n</div></div>\n</div>\n</div>]"
        },
        {
            "url": "?tekst=15731",
            "title": "Pokreni me",
            "lyrics": "[<div id=\"content-right\">\n<div id=\"content-padding\">\n<b><a href=\"?izvodjac=202\">Massimo Savi\u0107</a> - Pokreni me</b><br/>\n<br/>Jutro je, u jutru mi<br/>i sve je kao obicno<br/>u prvi tren kroz zavjese<br/>na sretne ljude slicimo<br/><br/>A jednom zeljeli smo<br/>sad ne znam sto<br/>odjednom nam je nevazno<br/><br/>Pokreni me, promijeni me<br/>i na pocetak vrati me<br/>jos jedan put da znam<br/>da postoji ljubav za nas oboje<br/><br/>Gledam te, ti gledas me<br/>i ko zna koga vidimo<br/><br/>A jednom zeljeli smo<br/>sad ne znam sto<br/>odjednom nam je nevazno<br/><br/>REFREN 2x<br/>Pokreni me, promijeni me<br/>i na pocetak vrati me<br/>jos jedan put da znam<br/>da se ljubav zove to sto trebam<br/><br/>Ti pokreni me<br/>i na pocetak vrati me<br/>jos jedan put da znam<br/>da postoji ljubav za nas oboje<br/><br/><div style=\"float: none; display: inline-block;\">\n<div style=\"display: inline-block; width: 468px; float: left; margin: 5px 5px 0px 0px; padding: 5px;\">\n<script async=\"\" src=\"//pagead2.googlesyndication.com/pagead/js/adsbygoogle.js\"></script>\n<!-- sv-muz-tekst-468x60 -->\n<ins class=\"adsbygoogle\" data-ad-client=\"ca-pub-7280186603976417\" data-ad-slot=\"4469454054\" style=\"display:inline-block;width:468px;height:60px\"></ins>\n<script>\n\t\t\t\t(adsbygoogle = window.adsbygoogle || []).push({});\n\t\t\t\t</script>\n</div>\n<div id=\"extra\">\n<div style=\"float: none; display: inline-block;\">\n\t\t\t\tPodelite:<br/><a href=\"http://www.facebook.com/sharer.php?u=http%3A%2F%2Fwww.svastara.com%2Fmuzika%2F%3Ftekst%3D15731\"><img alt=\"Share on Facebook\" border=\"0\" src=\"/style/2015/share_facebook.gif\" title=\"Share on Facebook\"/></a>\u00a0\u00a0<a href=\"http://twitter.com/intent/tweet?url=http%3A%2F%2Fwww.svastara.com%2Fmuzika%2F%3Ftekst%3D15731\"><img alt=\"Share on Twitter\" border=\"0\" src=\"/style/2015/share_twitter.gif\" title=\"Share on Twitter\"/></a>\u00a0\u00a0<a href=\"mailto:?subject=Massimo Savi\u0107 - Pokreni me tekst&amp;body=http%3A%2F%2Fwww.svastara.com%2Fmuzika%2F%3Ftekst%3D15731\"><img alt=\"Share by e-mail\" border=\"0\" src=\"/style/2015/share_email.gif\" title=\"Share by e-mail\"/></a>\n</div>\n<br/><img src=\"/style/2015/line_green.png\"/>\n<br/>\n<br/><div class=\"sidelist_header\">Popularni tekstovi</div><a href=\"?tekst=3068\" id=\"sidelist\">Stranac u no\u0107i</a><a href=\"?tekst=10390\" id=\"sidelist\">Odjednom</a><a href=\"?tekst=15102\" id=\"sidelist\">Karta devera</a><a href=\"?tekst=14824\" id=\"sidelist\">Da mogu</a><a href=\"?tekst=3067\" id=\"sidelist\">Sunce sija, trava miri\u0161e</a><a href=\"?tekst=11379\" id=\"sidelist\">Kad \u010dovjek voli \u017eenu</a><a href=\"?tekst=15544\" id=\"sidelist\">Benzina</a></div></div>\n</div>\n</div>]"
        },
        {
            "url": "?tekst=15547",
            "title": "Prokleto dobro znam",
            "lyrics": "[<div id=\"content-right\">\n<div id=\"content-padding\">\n<b><a href=\"?izvodjac=202\">Massimo Savi\u0107</a> - Prokleto dobro znam</b><br/>\n<br/>Jos uvijek oziljke u srcu nosim<br/>i vrijeme gazi me nogama bosim<br/>od straha ne vidim nista, nit cujem<br/>ja odavno samujem<br/><br/>U dusi svojoj sam stranac iz tame<br/>jer lazi ratuju oduvijek same<br/>al samo jedno me uz zivot veze<br/>al to mi je najteze<br/><br/>REFREN<br/>Jer nikoga ne znam bolje od sebe<br/>i znam kad je sunce tamno zbog mene<br/>i sto vise boli nosim u sebi<br/>sve jaci sam<br/>to prokleto dobro znam<br/><br/>Ja vec zivotu odavno pisem<br/>al moje stihove sudbina brise<br/>i sve sto pozelim drugom je sreca<br/>a to me podsjeca<br/><br/>REFREN 2x<br/><br/>Samo da nadjem put<br/>koji me vodi do moga neba<br/>samo da pronadjem put<br/><br/>REFREN<br/><br/><font color=\"green\"><i>- hvala Linda</i></font><br/><br/><div style=\"float: none; display: inline-block;\">\n<div style=\"display: inline-block; width: 468px; float: left; margin: 5px 5px 0px 0px; padding: 5px;\">\n<script async=\"\" src=\"//pagead2.googlesyndication.com/pagead/js/adsbygoogle.js\"></script>\n<!-- sv-muz-tekst-468x60 -->\n<ins class=\"adsbygoogle\" data-ad-client=\"ca-pub-7280186603976417\" data-ad-slot=\"4469454054\" style=\"display:inline-block;width:468px;height:60px\"></ins>\n<script>\n\t\t\t\t(adsbygoogle = window.adsbygoogle || []).push({});\n\t\t\t\t</script>\n</div>\n<div id=\"extra\">\n<div style=\"float: none; display: inline-block;\">\n\t\t\t\tPodelite:<br/><a href=\"http://www.facebook.com/sharer.php?u=http%3A%2F%2Fwww.svastara.com%2Fmuzika%2F%3Ftekst%3D15547\"><img alt=\"Share on Facebook\" border=\"0\" src=\"/style/2015/share_facebook.gif\" title=\"Share on Facebook\"/></a>\u00a0\u00a0<a href=\"http://twitter.com/intent/tweet?url=http%3A%2F%2Fwww.svastara.com%2Fmuzika%2F%3Ftekst%3D15547\"><img alt=\"Share on Twitter\" border=\"0\" src=\"/style/2015/share_twitter.gif\" title=\"Share on Twitter\"/></a>\u00a0\u00a0<a href=\"mailto:?subject=Massimo Savi\u0107 - Prokleto dobro znam tekst&amp;body=http%3A%2F%2Fwww.svastara.com%2Fmuzika%2F%3Ftekst%3D15547\"><img alt=\"Share by e-mail\" border=\"0\" src=\"/style/2015/share_email.gif\" title=\"Share by e-mail\"/></a>\n</div>\n<br/><img src=\"/style/2015/line_green.png\"/>\n<br/>\n<br/><div class=\"sidelist_header\">Popularni tekstovi</div><a href=\"?tekst=3068\" id=\"sidelist\">Stranac u no\u0107i</a><a href=\"?tekst=10390\" id=\"sidelist\">Odjednom</a><a href=\"?tekst=15102\" id=\"sidelist\">Karta devera</a><a href=\"?tekst=14824\" id=\"sidelist\">Da mogu</a><a href=\"?tekst=3067\" id=\"sidelist\">Sunce sija, trava miri\u0161e</a><a href=\"?tekst=11379\" id=\"sidelist\">Kad \u010dovjek voli \u017eenu</a><a href=\"?tekst=15544\" id=\"sidelist\">Benzina</a></div></div>\n</div>\n</div>]"
        },
        {
            "url": "?tekst=15730",
            "title": "Razlog",
            "lyrics": "[<div id=\"content-right\">\n<div id=\"content-padding\">\n<b><a href=\"?izvodjac=202\">Massimo Savi\u0107</a> - Razlog</b><br/>\n<br/>Kad sa mnom nisi tu<br/>ja dalje sam ne mogu<br/>ne podnosim tisinu<br/>fali mi tvoj smijeh<br/><br/>Sjaj i dugi muk<br/>pod nebom ispod zvijezda<br/>a nije bilo dobro<br/>i strah me je<br/><br/>REFREN<br/>Pa, pa, para<br/>o, ko si ti, ko si ti, da li te poznajem<br/>daj mi razlog da budem tu<br/>daj mi razlog da vratim ti se ja<br/>daj mi razlog da ljubim te<br/>bar jedan razlog mi daj<br/><br/>Gdje te misli nose<br/>na obale daleke<br/>a jednom kada odes<br/>za nas je blizu kraj<br/><br/>Pod nogama su puti<br/>treba li ih prijeci<br/>i dokle cemo doci<br/>ne znam ni sam<br/><br/>REFREN<br/><br/><font color=\"green\"><i>- hvala Limit</i></font><br/><br/><br/><div style=\"float: none; display: inline-block;\">\n<div id=\"extra\">\n<div style=\"float: none; display: inline-block;\">\n\t\t\t\tPodelite:<br/><a href=\"http://www.facebook.com/sharer.php?u=http%3A%2F%2Fwww.svastara.com%2Fmuzika%2F%3Ftekst%3D15730\"><img alt=\"Share on Facebook\" border=\"0\" src=\"/style/2015/share_facebook.gif\" title=\"Share on Facebook\"/></a>\u00a0\u00a0<a href=\"http://twitter.com/intent/tweet?url=http%3A%2F%2Fwww.svastara.com%2Fmuzika%2F%3Ftekst%3D15730\"><img alt=\"Share on Twitter\" border=\"0\" src=\"/style/2015/share_twitter.gif\" title=\"Share on Twitter\"/></a>\u00a0\u00a0<a href=\"mailto:?subject=Massimo Savi\u0107 - Razlog tekst&amp;body=http%3A%2F%2Fwww.svastara.com%2Fmuzika%2F%3Ftekst%3D15730\"><img alt=\"Share by e-mail\" border=\"0\" src=\"/style/2015/share_email.gif\" title=\"Share by e-mail\"/></a>\n</div>\n<br/><img src=\"/style/2015/line_green.png\"/>\n<br/>\n<br/><div class=\"sidelist_header\">Popularni tekstovi</div><a href=\"?tekst=3068\" id=\"sidelist\">Stranac u no\u0107i</a><a href=\"?tekst=10390\" id=\"sidelist\">Odjednom</a><a href=\"?tekst=15102\" id=\"sidelist\">Karta devera</a><a href=\"?tekst=14824\" id=\"sidelist\">Da mogu</a><a href=\"?tekst=3067\" id=\"sidelist\">Sunce sija, trava miri\u0161e</a><a href=\"?tekst=11379\" id=\"sidelist\">Kad \u010dovjek voli \u017eenu</a><a href=\"?tekst=15544\" id=\"sidelist\">Benzina</a></div>\n<div id=\"extra\">\n<script async=\"\" src=\"//pagead2.googlesyndication.com/pagead/js/adsbygoogle.js\"></script>\n<!-- sv-muz-tekst-300x250 -->\n<ins class=\"adsbygoogle\" data-ad-client=\"ca-pub-7280186603976417\" data-ad-slot=\"4744088596\" style=\"display:inline-block;width:300px;height:250px\"></ins>\n<script>\n\t\t\t\t(adsbygoogle = window.adsbygoogle || []).push({});\n\t\t\t\t</script>\n</div></div>\n</div>\n</div>]"
        },
        {
            "url": "?tekst=5419",
            "title": "Samo jedan dan",
            "lyrics": "[<div id=\"content-right\">\n<div id=\"content-padding\">\n<b><a href=\"?izvodjac=202\">Massimo Savi\u0107</a> - Samo jedan dan</b><br/>\n<br/>Plave se kise po staklima<br/>tisina pstavlja trag<br/>ti nemas snage da oprostis<br/>a znam da jos sam ti drag<br/><br/>utjehe nema u rijecima <br/>duboki oruje glas<br/>sve vidis u mojim ocima<br/>ostani zbog nas<br/> <br/>samo jedan dan zaustavi vrijeme<br/>samo jedan dan za tebe i mene <br/>u oku tvom zvijezda al` volim te do neba<br/>ostani zbog nas,samo jedan dan<br/><br/><font color=\"green\"><i>- hvala sanela i bojan</i></font><br/><br/><br/><div style=\"float: none; display: inline-block;\">\n<div id=\"extra\">\n<div style=\"float: none; display: inline-block;\">\n\t\t\t\tPodelite:<br/><a href=\"http://www.facebook.com/sharer.php?u=http%3A%2F%2Fwww.svastara.com%2Fmuzika%2F%3Ftekst%3D5419\"><img alt=\"Share on Facebook\" border=\"0\" src=\"/style/2015/share_facebook.gif\" title=\"Share on Facebook\"/></a>\u00a0\u00a0<a href=\"http://twitter.com/intent/tweet?url=http%3A%2F%2Fwww.svastara.com%2Fmuzika%2F%3Ftekst%3D5419\"><img alt=\"Share on Twitter\" border=\"0\" src=\"/style/2015/share_twitter.gif\" title=\"Share on Twitter\"/></a>\u00a0\u00a0<a href=\"mailto:?subject=Massimo Savi\u0107 - Samo jedan dan tekst&amp;body=http%3A%2F%2Fwww.svastara.com%2Fmuzika%2F%3Ftekst%3D5419\"><img alt=\"Share by e-mail\" border=\"0\" src=\"/style/2015/share_email.gif\" title=\"Share by e-mail\"/></a>\n</div>\n<br/><img src=\"/style/2015/line_green.png\"/>\n<br/>\n<br/><div class=\"sidelist_header\">Popularni tekstovi</div><a href=\"?tekst=3068\" id=\"sidelist\">Stranac u no\u0107i</a><a href=\"?tekst=10390\" id=\"sidelist\">Odjednom</a><a href=\"?tekst=15102\" id=\"sidelist\">Karta devera</a><a href=\"?tekst=14824\" id=\"sidelist\">Da mogu</a><a href=\"?tekst=3067\" id=\"sidelist\">Sunce sija, trava miri\u0161e</a><a href=\"?tekst=11379\" id=\"sidelist\">Kad \u010dovjek voli \u017eenu</a><a href=\"?tekst=15544\" id=\"sidelist\">Benzina</a></div>\n<div id=\"extra\">\n<script async=\"\" src=\"//pagead2.googlesyndication.com/pagead/js/adsbygoogle.js\"></script>\n<!-- sv-muz-tekst-300x250 -->\n<ins class=\"adsbygoogle\" data-ad-client=\"ca-pub-7280186603976417\" data-ad-slot=\"4744088596\" style=\"display:inline-block;width:300px;height:250px\"></ins>\n<script>\n\t\t\t\t(adsbygoogle = window.adsbygoogle || []).push({});\n\t\t\t\t</script>\n</div></div>\n</div>\n</div>]"
        },
        {
            "url": "?tekst=12731",
            "title": "Sjaj u tami",
            "lyrics": "[<div id=\"content-right\">\n<div id=\"content-padding\">\n<b><a href=\"?izvodjac=202\">Massimo Savi\u0107</a> - Sjaj u tami</b><br/>\n<br/>Dolazim i gradom nestajem<br/>Zaboravljam strah<br/>Usporavam korake<br/><br/>Gledaj moje ruke gledaj san<br/>Primakni svoje tjelo toplo je<br/>Pogledaj nije jos dan<br/>Padaju zvjezde oooouu<br/><br/>Oboji se sve<br/>Otvore vrata<br/>I vidis svjet kraj nas<br/><br/>Gledaj moje ruke gledaj san<br/>Primakni svoje tjelo toplo je..<br/>Gledaj moje oci gledaj sjaj<br/>Sjaj u tamiiii....<br/><br/><font color=\"green\"><i>- hvala candy</i></font><br/><br/><br/><div style=\"float: none; display: inline-block;\">\n<div id=\"extra\">\n<div style=\"float: none; display: inline-block;\">\n\t\t\t\tPodelite:<br/><a href=\"http://www.facebook.com/sharer.php?u=http%3A%2F%2Fwww.svastara.com%2Fmuzika%2F%3Ftekst%3D12731\"><img alt=\"Share on Facebook\" border=\"0\" src=\"/style/2015/share_facebook.gif\" title=\"Share on Facebook\"/></a>\u00a0\u00a0<a href=\"http://twitter.com/intent/tweet?url=http%3A%2F%2Fwww.svastara.com%2Fmuzika%2F%3Ftekst%3D12731\"><img alt=\"Share on Twitter\" border=\"0\" src=\"/style/2015/share_twitter.gif\" title=\"Share on Twitter\"/></a>\u00a0\u00a0<a href=\"mailto:?subject=Massimo Savi\u0107 - Sjaj u tami tekst&amp;body=http%3A%2F%2Fwww.svastara.com%2Fmuzika%2F%3Ftekst%3D12731\"><img alt=\"Share by e-mail\" border=\"0\" src=\"/style/2015/share_email.gif\" title=\"Share by e-mail\"/></a>\n</div>\n<br/><img src=\"/style/2015/line_green.png\"/>\n<br/>\n<br/><div class=\"sidelist_header\">Popularni tekstovi</div><a href=\"?tekst=3068\" id=\"sidelist\">Stranac u no\u0107i</a><a href=\"?tekst=10390\" id=\"sidelist\">Odjednom</a><a href=\"?tekst=15102\" id=\"sidelist\">Karta devera</a><a href=\"?tekst=14824\" id=\"sidelist\">Da mogu</a><a href=\"?tekst=3067\" id=\"sidelist\">Sunce sija, trava miri\u0161e</a><a href=\"?tekst=11379\" id=\"sidelist\">Kad \u010dovjek voli \u017eenu</a><a href=\"?tekst=15544\" id=\"sidelist\">Benzina</a></div>\n<div id=\"extra\">\n<script async=\"\" src=\"//pagead2.googlesyndication.com/pagead/js/adsbygoogle.js\"></script>\n<!-- sv-muz-tekst-300x250 -->\n<ins class=\"adsbygoogle\" data-ad-client=\"ca-pub-7280186603976417\" data-ad-slot=\"4744088596\" style=\"display:inline-block;width:300px;height:250px\"></ins>\n<script>\n\t\t\t\t(adsbygoogle = window.adsbygoogle || []).push({});\n\t\t\t\t</script>\n</div></div>\n</div>\n</div>]"
        },
        {
            "url": "?tekst=3068",
            "title": "Stranac u no\u0107i",
            "lyrics": "[<div id=\"content-right\">\n<div id=\"content-padding\">\n<b><a href=\"?izvodjac=202\">Massimo Savi\u0107</a> - Stranac u no\u0107i</b><br/>\n<br/>Znaju me svi, prodajem dusu zbog tebe,<br/>Zbog njeznosti, zbog ljubavi, zbog nas.<br/>Proslo je sve za tebe ja sam sad stranac u noci,<br/>A zelim te, i zovem te, wooooo<br/><br/>Pjevat cu dok usne me ne zabole,<br/>Ljubit cu dok usne mi ne izgore,<br/>Voljet cu dok oci se ne zatvore,<br/>Zauvijek ces biti tu.<br/><br/><font color=\"green\"><i>- hvala komarac</i></font><br/><br/><div style=\"float: none; display: inline-block;\">\n<div style=\"display: inline-block; width: 468px; float: left; margin: 5px 5px 0px 0px; padding: 5px;\">\n<script async=\"\" src=\"//pagead2.googlesyndication.com/pagead/js/adsbygoogle.js\"></script>\n<!-- sv-muz-tekst-468x60 -->\n<ins class=\"adsbygoogle\" data-ad-client=\"ca-pub-7280186603976417\" data-ad-slot=\"4469454054\" style=\"display:inline-block;width:468px;height:60px\"></ins>\n<script>\n\t\t\t\t(adsbygoogle = window.adsbygoogle || []).push({});\n\t\t\t\t</script>\n</div>\n<div id=\"extra\">\n<div style=\"float: none; display: inline-block;\">\n\t\t\t\tPodelite:<br/><a href=\"http://www.facebook.com/sharer.php?u=http%3A%2F%2Fwww.svastara.com%2Fmuzika%2F%3Ftekst%3D3068\"><img alt=\"Share on Facebook\" border=\"0\" src=\"/style/2015/share_facebook.gif\" title=\"Share on Facebook\"/></a>\u00a0\u00a0<a href=\"http://twitter.com/intent/tweet?url=http%3A%2F%2Fwww.svastara.com%2Fmuzika%2F%3Ftekst%3D3068\"><img alt=\"Share on Twitter\" border=\"0\" src=\"/style/2015/share_twitter.gif\" title=\"Share on Twitter\"/></a>\u00a0\u00a0<a href=\"mailto:?subject=Massimo Savi\u0107 - Stranac u no\u0107i tekst&amp;body=http%3A%2F%2Fwww.svastara.com%2Fmuzika%2F%3Ftekst%3D3068\"><img alt=\"Share by e-mail\" border=\"0\" src=\"/style/2015/share_email.gif\" title=\"Share by e-mail\"/></a>\n</div>\n<br/><img src=\"/style/2015/line_green.png\"/>\n<br/>\n<br/><div class=\"sidelist_header\">Popularni tekstovi</div><a href=\"?tekst=3068\" id=\"sidelist\">Stranac u no\u0107i</a><a href=\"?tekst=10390\" id=\"sidelist\">Odjednom</a><a href=\"?tekst=15102\" id=\"sidelist\">Karta devera</a><a href=\"?tekst=14824\" id=\"sidelist\">Da mogu</a><a href=\"?tekst=3067\" id=\"sidelist\">Sunce sija, trava miri\u0161e</a><a href=\"?tekst=11379\" id=\"sidelist\">Kad \u010dovjek voli \u017eenu</a><a href=\"?tekst=15544\" id=\"sidelist\">Benzina</a></div></div>\n</div>\n</div>]"
        },
        {
            "url": "?tekst=3067",
            "title": "Sunce sija, trava miri\u0161e",
            "lyrics": "[<div id=\"content-right\">\n<div id=\"content-padding\">\n<b><a href=\"?izvodjac=202\">Massimo Savi\u0107</a> - Sunce sija, trava miri\u0161e</b><br/>\n<br/>U mom kraju sad je prolje\u0107e,<br/>moja mama kuha najbolje.<br/>Okus tresnje na tvojim usnama,<br/>slatki nemir svud u grudima.<br/><br/>Mjesec gori iznad prozora,<br/>moja ljubav, rijeka duboka.<br/>U daljini svijetla pale se,<br/>vjetar nosi moje pozdrave.<br/><br/>Kad te vidim tuga nestaje,<br/>sija sunce, trava mirise.<br/>Srce moje kuca za tebe,<br/>najbolje je kad si kod ku\u0107e,<br/>kad si kod ku\u0107e.<br/><br/>U mom kraju svira muzika,<br/>ptice lete iznad oblaka,<br/>u daljini svijetla pale se,<br/>vjetar nosi moje pozdrave<br/><br/><font color=\"green\"><i>- hvala komarac</i></font><br/><br/><div style=\"float: none; display: inline-block;\">\n<div style=\"display: inline-block; width: 468px; float: left; margin: 5px 5px 0px 0px; padding: 5px;\">\n<script async=\"\" src=\"//pagead2.googlesyndication.com/pagead/js/adsbygoogle.js\"></script>\n<!-- sv-muz-tekst-468x60 -->\n<ins class=\"adsbygoogle\" data-ad-client=\"ca-pub-7280186603976417\" data-ad-slot=\"4469454054\" style=\"display:inline-block;width:468px;height:60px\"></ins>\n<script>\n\t\t\t\t(adsbygoogle = window.adsbygoogle || []).push({});\n\t\t\t\t</script>\n</div>\n<div id=\"extra\">\n<div style=\"float: none; display: inline-block;\">\n\t\t\t\tPodelite:<br/><a href=\"http://www.facebook.com/sharer.php?u=http%3A%2F%2Fwww.svastara.com%2Fmuzika%2F%3Ftekst%3D3067\"><img alt=\"Share on Facebook\" border=\"0\" src=\"/style/2015/share_facebook.gif\" title=\"Share on Facebook\"/></a>\u00a0\u00a0<a href=\"http://twitter.com/intent/tweet?url=http%3A%2F%2Fwww.svastara.com%2Fmuzika%2F%3Ftekst%3D3067\"><img alt=\"Share on Twitter\" border=\"0\" src=\"/style/2015/share_twitter.gif\" title=\"Share on Twitter\"/></a>\u00a0\u00a0<a href=\"mailto:?subject=Massimo Savi\u0107 - Sunce sija, trava miri\u0161e tekst&amp;body=http%3A%2F%2Fwww.svastara.com%2Fmuzika%2F%3Ftekst%3D3067\"><img alt=\"Share by e-mail\" border=\"0\" src=\"/style/2015/share_email.gif\" title=\"Share by e-mail\"/></a>\n</div>\n<br/><img src=\"/style/2015/line_green.png\"/>\n<br/>\n<br/><div class=\"sidelist_header\">Popularni tekstovi</div><a href=\"?tekst=3068\" id=\"sidelist\">Stranac u no\u0107i</a><a href=\"?tekst=10390\" id=\"sidelist\">Odjednom</a><a href=\"?tekst=15102\" id=\"sidelist\">Karta devera</a><a href=\"?tekst=14824\" id=\"sidelist\">Da mogu</a><a href=\"?tekst=3067\" id=\"sidelist\">Sunce sija, trava miri\u0161e</a><a href=\"?tekst=11379\" id=\"sidelist\">Kad \u010dovjek voli \u017eenu</a><a href=\"?tekst=15544\" id=\"sidelist\">Benzina</a></div></div>\n</div>\n</div>]"
        },
        {
            "url": "?tekst=21620",
            "title": "Trazi me",
            "lyrics": "[<div id=\"content-right\">\n<div id=\"content-padding\">\n<b><a href=\"?izvodjac=202\">Massimo Savi\u0107</a> - Trazi me</b><br/>\n<br/>trazi me<br/>kako hoces i ma gdje<br/>trazi me<br/>jos ti mogu pruzit sve<br/>trazi me<br/>i ne samo kad me trebas bez potrebe<br/>sa strahom i sa nadom izmisli me<br/><br/>trazi me<br/>kad sam sam i napadan<br/>trazi me<br/>kad sam lud i zabavan<br/>ja sam oduvjek takav<br/>il tezak il lak<br/>sve je to moja draga<br/>sve je to ljubavni znak<br/><br/><br/>ovaj zivot vec me kaznio<br/>ti znas pola istine<br/>a jos toliko je u meni<br/>danas pravom mukom cinim sve<br/>nasa radost skoro lazna<br/>tako gorko je treznjenje<br/><br/>i sad sam tu<br/>uvrjedi me i rani me<br/>takav sam ja<br/>izbrisi me<br/>ili primi me<br/>znam da ces rjec<br/>da nisam ja taj pravi covjek kakvog cekas<br/><br/>zivjet cu ja uz nesigurnost sto mi das<br/>zivjet cu ja uz malo sto mi ostavljas<br/>zivjet cu ja<br/>i ja bih htio da sam mladji<br/>a ti me nadji<br/><br/><br/>vjeruj mi<br/>za sve ima vremena<br/>vjeruj mi<br/>bice mnogih promjena<br/>sad sam ono sto vidis<br/>al odbacicu sve<br/>ako vjerujes malo i ne prestanes traziti me<br/><br/><br/>ovaj zivot vec me kaznio<br/>ti znas pola istine a jos toliko je u meni<br/>danas pravom mukom cinim sve<br/>nasa radost skoro lazna<br/>tako gorko je treznjenje<br/><br/>i sad sam tu<br/>uvrjedi me i rani me<br/>takav sam ja<br/>izbrisi me<br/>ili primi me<br/>znam da ces rjec<br/>da nisam ja taj pravi covjek kakvog cekas<br/><br/>zivjet cu ja uz nesigurnost sto mi das<br/>zivjet cu ja uz malo sto mi ostavljas<br/>zivjet cu ja<br/>i ja bih htio da sam mladji<br/>a ti me nadji<br/><br/>pronadji me,<br/>pronadji me,<br/>pronadji me,<br/>pronadji me...<br/><br/><font color=\"green\"><i>- hvala LiveForever</i></font><br/><br/><div style=\"float: none; display: inline-block;\">\n<div style=\"display: inline-block; width: 468px; float: left; margin: 5px 5px 0px 0px; padding: 5px;\">\n<script async=\"\" src=\"//pagead2.googlesyndication.com/pagead/js/adsbygoogle.js\"></script>\n<!-- sv-muz-tekst-468x60 -->\n<ins class=\"adsbygoogle\" data-ad-client=\"ca-pub-7280186603976417\" data-ad-slot=\"4469454054\" style=\"display:inline-block;width:468px;height:60px\"></ins>\n<script>\n\t\t\t\t(adsbygoogle = window.adsbygoogle || []).push({});\n\t\t\t\t</script>\n</div>\n<div id=\"extra\">\n<div style=\"float: none; display: inline-block;\">\n\t\t\t\tPodelite:<br/><a href=\"http://www.facebook.com/sharer.php?u=http%3A%2F%2Fwww.svastara.com%2Fmuzika%2F%3Ftekst%3D21620\"><img alt=\"Share on Facebook\" border=\"0\" src=\"/style/2015/share_facebook.gif\" title=\"Share on Facebook\"/></a>\u00a0\u00a0<a href=\"http://twitter.com/intent/tweet?url=http%3A%2F%2Fwww.svastara.com%2Fmuzika%2F%3Ftekst%3D21620\"><img alt=\"Share on Twitter\" border=\"0\" src=\"/style/2015/share_twitter.gif\" title=\"Share on Twitter\"/></a>\u00a0\u00a0<a href=\"mailto:?subject=Massimo Savi\u0107 - Trazi me tekst&amp;body=http%3A%2F%2Fwww.svastara.com%2Fmuzika%2F%3Ftekst%3D21620\"><img alt=\"Share by e-mail\" border=\"0\" src=\"/style/2015/share_email.gif\" title=\"Share by e-mail\"/></a>\n</div>\n<br/><img src=\"/style/2015/line_green.png\"/>\n<br/>\n<br/><div class=\"sidelist_header\">Popularni tekstovi</div><a href=\"?tekst=3068\" id=\"sidelist\">Stranac u no\u0107i</a><a href=\"?tekst=10390\" id=\"sidelist\">Odjednom</a><a href=\"?tekst=15102\" id=\"sidelist\">Karta devera</a><a href=\"?tekst=14824\" id=\"sidelist\">Da mogu</a><a href=\"?tekst=3067\" id=\"sidelist\">Sunce sija, trava miri\u0161e</a><a href=\"?tekst=11379\" id=\"sidelist\">Kad \u010dovjek voli \u017eenu</a><a href=\"?tekst=15544\" id=\"sidelist\">Benzina</a></div></div>\n</div>\n</div>]"
        },
        {
            "url": "?tekst=15545",
            "title": "Tu na mojim rukama",
            "lyrics": "[<div id=\"content-right\">\n<div id=\"content-padding\">\n<b><a href=\"?izvodjac=202\">Massimo Savi\u0107</a> - Tu na mojim rukama</b><br/>\n<br/>Rodjen sam da cinim greske<br/>i da hocu ne znam bolje<br/>usne su mi tako teske<br/>kada dotaknu tvoje<br/><br/>Sad ni suza nemam vise<br/>da te nijemo pratim samo<br/>vrijeme uspomene brise<br/>to i ti i ja znamo<br/><br/>REFREN<br/>Tu na mojim rukama<br/>ova ljubav umire<br/>dok nam jutro umorno<br/>broji zadnje dodire<br/><br/>Srece nema u nama<br/>gubi joj se svaki trag<br/>gdje su oni dani svi<br/>kad sam tebi bio drag<br/><br/>Znam da nema vise vremena za nas<br/>ja zadnji put te ljubim danas<br/>nesto pricas, ali ne cujem ti gals<br/><br/>REFREN<br/><br/><font color=\"green\"><i>- hvala Linda</i></font><br/><br/><div style=\"float: none; display: inline-block;\">\n<div style=\"display: inline-block; width: 468px; float: left; margin: 5px 5px 0px 0px; padding: 5px;\">\n<script async=\"\" src=\"//pagead2.googlesyndication.com/pagead/js/adsbygoogle.js\"></script>\n<!-- sv-muz-tekst-468x60 -->\n<ins class=\"adsbygoogle\" data-ad-client=\"ca-pub-7280186603976417\" data-ad-slot=\"4469454054\" style=\"display:inline-block;width:468px;height:60px\"></ins>\n<script>\n\t\t\t\t(adsbygoogle = window.adsbygoogle || []).push({});\n\t\t\t\t</script>\n</div>\n<div id=\"extra\">\n<div style=\"float: none; display: inline-block;\">\n\t\t\t\tPodelite:<br/><a href=\"http://www.facebook.com/sharer.php?u=http%3A%2F%2Fwww.svastara.com%2Fmuzika%2F%3Ftekst%3D15545\"><img alt=\"Share on Facebook\" border=\"0\" src=\"/style/2015/share_facebook.gif\" title=\"Share on Facebook\"/></a>\u00a0\u00a0<a href=\"http://twitter.com/intent/tweet?url=http%3A%2F%2Fwww.svastara.com%2Fmuzika%2F%3Ftekst%3D15545\"><img alt=\"Share on Twitter\" border=\"0\" src=\"/style/2015/share_twitter.gif\" title=\"Share on Twitter\"/></a>\u00a0\u00a0<a href=\"mailto:?subject=Massimo Savi\u0107 - Tu na mojim rukama tekst&amp;body=http%3A%2F%2Fwww.svastara.com%2Fmuzika%2F%3Ftekst%3D15545\"><img alt=\"Share by e-mail\" border=\"0\" src=\"/style/2015/share_email.gif\" title=\"Share by e-mail\"/></a>\n</div>\n<br/><img src=\"/style/2015/line_green.png\"/>\n<br/>\n<br/><div class=\"sidelist_header\">Popularni tekstovi</div><a href=\"?tekst=3068\" id=\"sidelist\">Stranac u no\u0107i</a><a href=\"?tekst=10390\" id=\"sidelist\">Odjednom</a><a href=\"?tekst=15102\" id=\"sidelist\">Karta devera</a><a href=\"?tekst=14824\" id=\"sidelist\">Da mogu</a><a href=\"?tekst=3067\" id=\"sidelist\">Sunce sija, trava miri\u0161e</a><a href=\"?tekst=11379\" id=\"sidelist\">Kad \u010dovjek voli \u017eenu</a><a href=\"?tekst=15544\" id=\"sidelist\">Benzina</a></div></div>\n</div>\n</div>]"
        },
        {
            "url": "?tekst=21623",
            "title": "Zar vise nema nas",
            "lyrics": "[<div id=\"content-right\">\n<div id=\"content-padding\">\n<b><a href=\"?izvodjac=202\">Massimo Savi\u0107</a> - Zar vise nema nas</b><br/>\n<br/>Od vremena tog,<br/>Bez dodira tvog,<br/>Za tren su pro\u0161la ljeta i zime,<br/>Njeno su lice isprale ki\u0161e,<br/>Njene su rije\u010di sve ti\u0161e i ti\u0161e.<br/><br/>Kad pogledam sebi, ravno u o\u010di,<br/>Shvatim da \u017eivim u gorkoj samo\u0107i,<br/>Ljubav sad ima, kameno lice,<br/>Ja razmi\u0161ljam, jesam li jo\u0161 uvijek mlad<br/>Oblaci te\u0161ki, kad bi bar htjeli, nestat na \u010das.<br/><br/>Ja razmi\u0161ljam sad jesam li jo\u0161 uvijek mlad,<br/>Oblaci te\u0161ki, kad bi bar htjeli nestat na \u010das,<br/>Zar vi\u0161e nema nas?<br/><br/><font color=\"green\"><i>- hvala Srna</i></font><br/><br/><br/><div style=\"float: none; display: inline-block;\">\n<div id=\"extra\">\n<div style=\"float: none; display: inline-block;\">\n\t\t\t\tPodelite:<br/><a href=\"http://www.facebook.com/sharer.php?u=http%3A%2F%2Fwww.svastara.com%2Fmuzika%2F%3Ftekst%3D21623\"><img alt=\"Share on Facebook\" border=\"0\" src=\"/style/2015/share_facebook.gif\" title=\"Share on Facebook\"/></a>\u00a0\u00a0<a href=\"http://twitter.com/intent/tweet?url=http%3A%2F%2Fwww.svastara.com%2Fmuzika%2F%3Ftekst%3D21623\"><img alt=\"Share on Twitter\" border=\"0\" src=\"/style/2015/share_twitter.gif\" title=\"Share on Twitter\"/></a>\u00a0\u00a0<a href=\"mailto:?subject=Massimo Savi\u0107 - Zar vise nema nas tekst&amp;body=http%3A%2F%2Fwww.svastara.com%2Fmuzika%2F%3Ftekst%3D21623\"><img alt=\"Share by e-mail\" border=\"0\" src=\"/style/2015/share_email.gif\" title=\"Share by e-mail\"/></a>\n</div>\n<br/><img src=\"/style/2015/line_green.png\"/>\n<br/>\n<br/><div class=\"sidelist_header\">Popularni tekstovi</div><a href=\"?tekst=3068\" id=\"sidelist\">Stranac u no\u0107i</a><a href=\"?tekst=10390\" id=\"sidelist\">Odjednom</a><a href=\"?tekst=15102\" id=\"sidelist\">Karta devera</a><a href=\"?tekst=14824\" id=\"sidelist\">Da mogu</a><a href=\"?tekst=3067\" id=\"sidelist\">Sunce sija, trava miri\u0161e</a><a href=\"?tekst=11379\" id=\"sidelist\">Kad \u010dovjek voli \u017eenu</a><a href=\"?tekst=15544\" id=\"sidelist\">Benzina</a></div>\n<div id=\"extra\">\n<script async=\"\" src=\"//pagead2.googlesyndication.com/pagead/js/adsbygoogle.js\"></script>\n<!-- sv-muz-tekst-300x250 -->\n<ins class=\"adsbygoogle\" data-ad-client=\"ca-pub-7280186603976417\" data-ad-slot=\"4744088596\" style=\"display:inline-block;width:300px;height:250px\"></ins>\n<script>\n\t\t\t\t(adsbygoogle = window.adsbygoogle || []).push({});\n\t\t\t\t</script>\n</div></div>\n</div>\n</div>]"
        },
        {
            "url": "?tekst=21588",
            "title": "Zar vise nema nas (Feat. Neno Belan)",
            "lyrics": "[<div id=\"content-right\">\n<div id=\"content-padding\">\n<b><a href=\"?izvodjac=202\">Massimo Savi\u0107</a> - Zar vise nema nas (Feat. Neno Belan)</b><br/>\n<br/>Od vremena tog bez dodira tvog<br/>Za tren su prosla ljeta i zime<br/>Njeno su lice isprale kise<br/>Njene su rijeci sve tise i tise<br/><br/>Kad pogledam sebi ravno u oci<br/>Shvatim da zivim u gorkoj samoci<br/>Ljubav sad ima kameno lice,<br/>ja razmisljam...<br/><br/>Jesam li jos uvjek mlad<br/>Oblaci teski kad bi bar htjeli<br/>Nestat na cas<br/><br/>Ja razmisljam sad<br/>Jesam li jos uvjek mlad<br/>Oblaci teski kad bi bar htjeli nestat na cas<br/>Zar vise nema nas<br/><br/><font color=\"green\"><i>- hvala Next Bocca</i></font><br/><br/><br/><div style=\"float: none; display: inline-block;\">\n<div id=\"extra\">\n<div style=\"float: none; display: inline-block;\">\n\t\t\t\tPodelite:<br/><a href=\"http://www.facebook.com/sharer.php?u=http%3A%2F%2Fwww.svastara.com%2Fmuzika%2F%3Ftekst%3D21588\"><img alt=\"Share on Facebook\" border=\"0\" src=\"/style/2015/share_facebook.gif\" title=\"Share on Facebook\"/></a>\u00a0\u00a0<a href=\"http://twitter.com/intent/tweet?url=http%3A%2F%2Fwww.svastara.com%2Fmuzika%2F%3Ftekst%3D21588\"><img alt=\"Share on Twitter\" border=\"0\" src=\"/style/2015/share_twitter.gif\" title=\"Share on Twitter\"/></a>\u00a0\u00a0<a href=\"mailto:?subject=Massimo Savi\u0107 - Zar vise nema nas (Feat. Neno Belan) tekst&amp;body=http%3A%2F%2Fwww.svastara.com%2Fmuzika%2F%3Ftekst%3D21588\"><img alt=\"Share by e-mail\" border=\"0\" src=\"/style/2015/share_email.gif\" title=\"Share by e-mail\"/></a>\n</div>\n<br/><img src=\"/style/2015/line_green.png\"/>\n<br/>\n<br/><div class=\"sidelist_header\">Popularni tekstovi</div><a href=\"?tekst=3068\" id=\"sidelist\">Stranac u no\u0107i</a><a href=\"?tekst=10390\" id=\"sidelist\">Odjednom</a><a href=\"?tekst=15102\" id=\"sidelist\">Karta devera</a><a href=\"?tekst=14824\" id=\"sidelist\">Da mogu</a><a href=\"?tekst=3067\" id=\"sidelist\">Sunce sija, trava miri\u0161e</a><a href=\"?tekst=11379\" id=\"sidelist\">Kad \u010dovjek voli \u017eenu</a><a href=\"?tekst=15544\" id=\"sidelist\">Benzina</a></div>\n<div id=\"extra\">\n<script async=\"\" src=\"//pagead2.googlesyndication.com/pagead/js/adsbygoogle.js\"></script>\n<!-- sv-muz-tekst-300x250 -->\n<ins class=\"adsbygoogle\" data-ad-client=\"ca-pub-7280186603976417\" data-ad-slot=\"4744088596\" style=\"display:inline-block;width:300px;height:250px\"></ins>\n<script>\n\t\t\t\t(adsbygoogle = window.adsbygoogle || []).push({});\n\t\t\t\t</script>\n</div></div>\n</div>\n</div>]"
        },
        {
            "url": "?tekst=21591",
            "title": "Znam za\u0161to te osje\u0107am",
            "lyrics": "[<div id=\"content-right\">\n<div id=\"content-padding\">\n<b><a href=\"?izvodjac=202\">Massimo Savi\u0107</a> - Znam za\u0161to te osje\u0107am</b><br/>\n<br/>Sve ove godine,<br/>suhog tijela glad za toplim rukama<br/>Dan kojeg \u017eivimo,<br/>svaki za nas je bli\u017ee istini<br/>I nisam druk\u010diji, <br/>Samo slijedim to \u0161to srce ka\u017ee<br/>da ti si ta<br/><br/>Refern:<br/>Ja znam za\u0161to te osje\u0107am<br/>Ja znam da nisam tu bezveze<br/>Ja znam za\u0161to te osje\u0107am<br/>Jer nitko drugi nije dao ono \u0161to si ti za mene<br/><br/>Budimo samo to \u0161to jesmo<br/>jer gradimo novi svijet <br/>I nismo druk\u010diji <br/>Samo slijedimo  \u0161to srce ka\u017ee<br/>Jer svejedno<br/><br/>Ja znam za\u0161to te osje\u0107am<br/>Ja znam da nisam tu bezveze<br/>Ja znam za\u0161to te osje\u0107am<br/>Jer nitko drugi nije dao, <br/>Nitko drugi nije znao<br/><br/><font color=\"green\"><i>- hvala Marta S.</i></font><br/><br/><br/><div style=\"float: none; display: inline-block;\">\n<div id=\"extra\">\n<div style=\"float: none; display: inline-block;\">\n\t\t\t\tPodelite:<br/><a href=\"http://www.facebook.com/sharer.php?u=http%3A%2F%2Fwww.svastara.com%2Fmuzika%2F%3Ftekst%3D21591\"><img alt=\"Share on Facebook\" border=\"0\" src=\"/style/2015/share_facebook.gif\" title=\"Share on Facebook\"/></a>\u00a0\u00a0<a href=\"http://twitter.com/intent/tweet?url=http%3A%2F%2Fwww.svastara.com%2Fmuzika%2F%3Ftekst%3D21591\"><img alt=\"Share on Twitter\" border=\"0\" src=\"/style/2015/share_twitter.gif\" title=\"Share on Twitter\"/></a>\u00a0\u00a0<a href=\"mailto:?subject=Massimo Savi\u0107 - Znam za\u0161to te osje\u0107am tekst&amp;body=http%3A%2F%2Fwww.svastara.com%2Fmuzika%2F%3Ftekst%3D21591\"><img alt=\"Share by e-mail\" border=\"0\" src=\"/style/2015/share_email.gif\" title=\"Share by e-mail\"/></a>\n</div>\n<br/><img src=\"/style/2015/line_green.png\"/>\n<br/>\n<br/><div class=\"sidelist_header\">Popularni tekstovi</div><a href=\"?tekst=3068\" id=\"sidelist\">Stranac u no\u0107i</a><a href=\"?tekst=10390\" id=\"sidelist\">Odjednom</a><a href=\"?tekst=15102\" id=\"sidelist\">Karta devera</a><a href=\"?tekst=14824\" id=\"sidelist\">Da mogu</a><a href=\"?tekst=3067\" id=\"sidelist\">Sunce sija, trava miri\u0161e</a><a href=\"?tekst=11379\" id=\"sidelist\">Kad \u010dovjek voli \u017eenu</a><a href=\"?tekst=15544\" id=\"sidelist\">Benzina</a></div>\n<div id=\"extra\">\n<script async=\"\" src=\"//pagead2.googlesyndication.com/pagead/js/adsbygoogle.js\"></script>\n<!-- sv-muz-tekst-300x250 -->\n<ins class=\"adsbygoogle\" data-ad-client=\"ca-pub-7280186603976417\" data-ad-slot=\"4744088596\" style=\"display:inline-block;width:300px;height:250px\"></ins>\n<script>\n\t\t\t\t(adsbygoogle = window.adsbygoogle || []).push({});\n\t\t\t\t</script>\n</div></div>\n</div>\n</div>]"
        }
    ]
}