{
    "OKO": [
        {
            "url": "?tekst=17328",
            "title": "Kad si blizu",
            "lyrics": "[<div id=\"content-right\">\n<div id=\"content-padding\">\n<b><a href=\"?izvodjac=924\">OKO</a> - Kad si blizu</b><br/>\n<br/>Odjekuju teska zvona<br/>Ulica spava,<br/>Otkud stranci u mom snu<br/>Bilo bi ljepse da si tu pokraj mene<br/>Sve mi je ljepse kad si tu...<br/><br/>Tvoj miris po sobi trazim<br/>Zakljucavam ga<br/>Odjek tisine u krevetu<br/>Bilo bi ljepse da si tu<br/>Sve mi je ljepse kad si tu pokraj mene<br/>Kad si...<br/><br/>Kad si blizu...<br/><br/>Tako se dobro osjecam, kad si blizu...<br/>Uvjek se dobro osjecam, kad si blizu...<br/>Tako se dobro osjecam, kad si blizu...<br/>S tobom se dobro zabavljam, kad si blizu...<br/><br/><font color=\"green\"><i>- hvala cudija</i></font><br/><br/><div style=\"float: none; display: inline-block;\">\n<div style=\"display: inline-block; width: 468px; float: left; margin: 5px 5px 0px 0px; padding: 5px;\">\n<script async=\"\" src=\"//pagead2.googlesyndication.com/pagead/js/adsbygoogle.js\"></script>\n<!-- sv-muz-tekst-468x60 -->\n<ins class=\"adsbygoogle\" data-ad-client=\"ca-pub-7280186603976417\" data-ad-slot=\"4469454054\" style=\"display:inline-block;width:468px;height:60px\"></ins>\n<script>\n\t\t\t\t(adsbygoogle = window.adsbygoogle || []).push({});\n\t\t\t\t</script>\n</div>\n<div id=\"extra\">\n<div style=\"float: none; display: inline-block;\">\n\t\t\t\tPodelite:<br/><a href=\"http://www.facebook.com/sharer.php?u=http%3A%2F%2Fwww.svastara.com%2Fmuzika%2F%3Ftekst%3D17328\"><img alt=\"Share on Facebook\" border=\"0\" src=\"/style/2015/share_facebook.gif\" title=\"Share on Facebook\"/></a>\u00a0\u00a0<a href=\"http://twitter.com/intent/tweet?url=http%3A%2F%2Fwww.svastara.com%2Fmuzika%2F%3Ftekst%3D17328\"><img alt=\"Share on Twitter\" border=\"0\" src=\"/style/2015/share_twitter.gif\" title=\"Share on Twitter\"/></a>\u00a0\u00a0<a href=\"mailto:?subject=OKO - Kad si blizu tekst&amp;body=http%3A%2F%2Fwww.svastara.com%2Fmuzika%2F%3Ftekst%3D17328\"><img alt=\"Share by e-mail\" border=\"0\" src=\"/style/2015/share_email.gif\" title=\"Share by e-mail\"/></a>\n</div>\n<br/><img src=\"/style/2015/line_green.png\"/>\n<br/>\n<br/><div class=\"sidelist_header\">Popularni tekstovi</div><a href=\"?tekst=17326\" id=\"sidelist\">Treba mi ljubav tvoja</a><a href=\"?tekst=17327\" id=\"sidelist\">Opusti se</a><a href=\"?tekst=17328\" id=\"sidelist\">Kad si blizu</a></div></div>\n</div>\n</div>]"
        },
        {
            "url": "?tekst=17327",
            "title": "Opusti se",
            "lyrics": "[<div id=\"content-right\">\n<div id=\"content-padding\">\n<b><a href=\"?izvodjac=924\">OKO</a> - Opusti se</b><br/>\n<br/>Tebe mnoge stvari brinu<br/>Nisi vise smirena<br/>Ritam tvoga plesa je nesiguran hod<br/><br/>Prati odjek lakih koraka<br/>Za srercu dovoljni smo ti i ja i muzika <br/><br/>Budi mi jaka i ne dozvoli da <br/>Vjetar te baca iz tvojih cipela<br/>Ne obracaj paznju <br/>Nema razloga za bjes<br/>Lelujaj k'o lisce i <br/>Opusti se...<br/><br/>Srce udara<br/>Zvukom losih bubnjeva<br/>U tvome oku munja nebeska<br/>Srce udara <br/>kao mecevi od celika<br/>tuzan lagud u tvojim grudima...<br/><br/>nedaj da ti slome grane<br/>zamisli da sviraju<br/>daruj nekom malo sjaja<br/>tvojih ociju<br/><br/>prati odjek lakih koraka<br/>za srecu dovoljni smo ti i ja i muzika<br/><br/>Budi mi jaka i ne dozvoli da <br/>Vjetar te baca iz tvojih cipela<br/>Ne obracaj paznju <br/>Nema razloga za bjes<br/>Lelujaj k'o lisce i <br/><br/>Modulacija:<br/><br/>Budi mi jaka i ne dozvoli da <br/>Vjetar te baca iz tvojih cipela<br/>Ne obracaj paznju <br/>Nema razloga za bjes<br/>Lelujaj k'o lisce i <br/>Opusti se...<br/><br/><font color=\"green\"><i>- hvala cudija</i></font><br/><br/><div style=\"float: none; display: inline-block;\">\n<div style=\"display: inline-block; width: 468px; float: left; margin: 5px 5px 0px 0px; padding: 5px;\">\n<script async=\"\" src=\"//pagead2.googlesyndication.com/pagead/js/adsbygoogle.js\"></script>\n<!-- sv-muz-tekst-468x60 -->\n<ins class=\"adsbygoogle\" data-ad-client=\"ca-pub-7280186603976417\" data-ad-slot=\"4469454054\" style=\"display:inline-block;width:468px;height:60px\"></ins>\n<script>\n\t\t\t\t(adsbygoogle = window.adsbygoogle || []).push({});\n\t\t\t\t</script>\n</div>\n<div id=\"extra\">\n<div style=\"float: none; display: inline-block;\">\n\t\t\t\tPodelite:<br/><a href=\"http://www.facebook.com/sharer.php?u=http%3A%2F%2Fwww.svastara.com%2Fmuzika%2F%3Ftekst%3D17327\"><img alt=\"Share on Facebook\" border=\"0\" src=\"/style/2015/share_facebook.gif\" title=\"Share on Facebook\"/></a>\u00a0\u00a0<a href=\"http://twitter.com/intent/tweet?url=http%3A%2F%2Fwww.svastara.com%2Fmuzika%2F%3Ftekst%3D17327\"><img alt=\"Share on Twitter\" border=\"0\" src=\"/style/2015/share_twitter.gif\" title=\"Share on Twitter\"/></a>\u00a0\u00a0<a href=\"mailto:?subject=OKO - Opusti se tekst&amp;body=http%3A%2F%2Fwww.svastara.com%2Fmuzika%2F%3Ftekst%3D17327\"><img alt=\"Share by e-mail\" border=\"0\" src=\"/style/2015/share_email.gif\" title=\"Share by e-mail\"/></a>\n</div>\n<br/><img src=\"/style/2015/line_green.png\"/>\n<br/>\n<br/><div class=\"sidelist_header\">Popularni tekstovi</div><a href=\"?tekst=17326\" id=\"sidelist\">Treba mi ljubav tvoja</a><a href=\"?tekst=17327\" id=\"sidelist\">Opusti se</a><a href=\"?tekst=17328\" id=\"sidelist\">Kad si blizu</a></div></div>\n</div>\n</div>]"
        },
        {
            "url": "?tekst=17326",
            "title": "Treba mi ljubav tvoja",
            "lyrics": "[<div id=\"content-right\">\n<div id=\"content-padding\">\n<b><a href=\"?izvodjac=924\">OKO</a> - Treba mi ljubav tvoja</b><br/>\n<br/>Hocu nocas da me ljube<br/>Tvoje usne tresnje prezrele<br/>Da me pustis pod svoju kosulju<br/>Da mi sapces ti<br/>Da me lazes ti<br/>Kako nikog ne volis ko mene<br/>Poljubi me i zagrli me<br/>Stisni se uz mene<br/>Pomuti mi pamet, budi slobodna<br/>Budi moja<br/><br/>Treba mi ljubav tvoja<br/>Kao nikada prije<br/>Neka noc traje<br/>Koliko nikada nije....<br/><br/>Povedi me u nebo od pamuka i svile<br/>Da letimo kroz boje<br/>Zatvori oci svoje<br/>I ne prekidaj snove<br/><br/><font color=\"green\"><i>- hvala cudija</i></font><br/><br/><br/><div style=\"float: none; display: inline-block;\">\n<div id=\"extra\">\n<div style=\"float: none; display: inline-block;\">\n\t\t\t\tPodelite:<br/><a href=\"http://www.facebook.com/sharer.php?u=http%3A%2F%2Fwww.svastara.com%2Fmuzika%2F%3Ftekst%3D17326\"><img alt=\"Share on Facebook\" border=\"0\" src=\"/style/2015/share_facebook.gif\" title=\"Share on Facebook\"/></a>\u00a0\u00a0<a href=\"http://twitter.com/intent/tweet?url=http%3A%2F%2Fwww.svastara.com%2Fmuzika%2F%3Ftekst%3D17326\"><img alt=\"Share on Twitter\" border=\"0\" src=\"/style/2015/share_twitter.gif\" title=\"Share on Twitter\"/></a>\u00a0\u00a0<a href=\"mailto:?subject=OKO - Treba mi ljubav tvoja tekst&amp;body=http%3A%2F%2Fwww.svastara.com%2Fmuzika%2F%3Ftekst%3D17326\"><img alt=\"Share by e-mail\" border=\"0\" src=\"/style/2015/share_email.gif\" title=\"Share by e-mail\"/></a>\n</div>\n<br/><img src=\"/style/2015/line_green.png\"/>\n<br/>\n<br/><div class=\"sidelist_header\">Popularni tekstovi</div><a href=\"?tekst=17326\" id=\"sidelist\">Treba mi ljubav tvoja</a><a href=\"?tekst=17327\" id=\"sidelist\">Opusti se</a><a href=\"?tekst=17328\" id=\"sidelist\">Kad si blizu</a></div>\n<div id=\"extra\">\n<script async=\"\" src=\"//pagead2.googlesyndication.com/pagead/js/adsbygoogle.js\"></script>\n<!-- sv-muz-tekst-300x250 -->\n<ins class=\"adsbygoogle\" data-ad-client=\"ca-pub-7280186603976417\" data-ad-slot=\"4744088596\" style=\"display:inline-block;width:300px;height:250px\"></ins>\n<script>\n\t\t\t\t(adsbygoogle = window.adsbygoogle || []).push({});\n\t\t\t\t</script>\n</div></div>\n</div>\n</div>]"
        }
    ]
}